package com.google.android.common.base;

import java.util.HashSet;
import java.util.Map;
import java.util.Set;
import java.util.regex.Pattern;

public final class StringUtil
{
  private static final Set<Character.UnicodeBlock> CJK_BLOCKS;
  private static final CharMatcher CONTROL_MATCHER;
  static final Map<String, Character> ESCAPE_STRINGS;
  private static final CharMatcher FANCY_DOUBLE_QUOTE;
  private static final CharMatcher FANCY_SINGLE_QUOTE;
  private static final char[] HEX_CHARS;
  static final Set<Character> HEX_LETTERS;
  private static final CharEscaper JAVA_ESCAPE;
  private static final Set<Integer> JSON_ESCAPE_CHARS;
  private static final Set<Integer> JS_ESCAPE_CHARS;
  private static final CharEscaper LT_GT_ESCAPE;
  private static final Splitter NEWLINE_SPLITTER = Splitter.on(10).omitEmptyStrings();
  private static final char[] OCTAL_CHARS;
  private static final CharEscaper REGEX_ESCAPE;
  private static final Splitter TO_WORDS = Splitter.on(CharMatcher.BREAKING_WHITESPACE).omitEmptyStrings();
  private static final Pattern characterReferencePattern;
  private static final Pattern dbSpecPattern;
  private static final Pattern htmlTagPattern;

  // ERROR //
  static
  {
    // Byte code:
    //   0: bipush 10
    //   2: invokestatic 47	com/google/android/common/base/Splitter:on	(C)Lcom/google/android/common/base/Splitter;
    //   5: invokevirtual 51	com/google/android/common/base/Splitter:omitEmptyStrings	()Lcom/google/android/common/base/Splitter;
    //   8: putstatic 53	com/google/android/common/base/StringUtil:NEWLINE_SPLITTER	Lcom/google/android/common/base/Splitter;
    //   11: getstatic 58	com/google/android/common/base/CharMatcher:BREAKING_WHITESPACE	Lcom/google/android/common/base/CharMatcher;
    //   14: invokestatic 61	com/google/android/common/base/Splitter:on	(Lcom/google/android/common/base/CharMatcher;)Lcom/google/android/common/base/Splitter;
    //   17: invokevirtual 51	com/google/android/common/base/Splitter:omitEmptyStrings	()Lcom/google/android/common/base/Splitter;
    //   20: putstatic 63	com/google/android/common/base/StringUtil:TO_WORDS	Lcom/google/android/common/base/Splitter;
    //   23: ldc 65
    //   25: invokestatic 69	com/google/android/common/base/CharMatcher:anyOf	(Ljava/lang/CharSequence;)Lcom/google/android/common/base/CharMatcher;
    //   28: putstatic 71	com/google/android/common/base/StringUtil:FANCY_SINGLE_QUOTE	Lcom/google/android/common/base/CharMatcher;
    //   31: ldc 73
    //   33: invokestatic 69	com/google/android/common/base/CharMatcher:anyOf	(Ljava/lang/CharSequence;)Lcom/google/android/common/base/CharMatcher;
    //   36: putstatic 75	com/google/android/common/base/StringUtil:FANCY_DOUBLE_QUOTE	Lcom/google/android/common/base/CharMatcher;
    //   39: new 77	java/util/HashMap
    //   42: dup
    //   43: sipush 252
    //   46: invokespecial 81	java/util/HashMap:<init>	(I)V
    //   49: putstatic 83	com/google/android/common/base/StringUtil:ESCAPE_STRINGS	Ljava/util/Map;
    //   52: getstatic 83	com/google/android/common/base/StringUtil:ESCAPE_STRINGS	Ljava/util/Map;
    //   55: astore_0
    //   56: sipush 160
    //   59: invokestatic 89	java/lang/Character:valueOf	(C)Ljava/lang/Character;
    //   62: astore_1
    //   63: aload_0
    //   64: ldc 91
    //   66: aload_1
    //   67: invokeinterface 97 3 0
    //   72: astore_2
    //   73: getstatic 83	com/google/android/common/base/StringUtil:ESCAPE_STRINGS	Ljava/util/Map;
    //   76: astore_3
    //   77: sipush 161
    //   80: invokestatic 89	java/lang/Character:valueOf	(C)Ljava/lang/Character;
    //   83: astore 4
    //   85: aload_3
    //   86: ldc 99
    //   88: aload 4
    //   90: invokeinterface 97 3 0
    //   95: astore 5
    //   97: getstatic 83	com/google/android/common/base/StringUtil:ESCAPE_STRINGS	Ljava/util/Map;
    //   100: astore 6
    //   102: sipush 162
    //   105: invokestatic 89	java/lang/Character:valueOf	(C)Ljava/lang/Character;
    //   108: astore 7
    //   110: aload 6
    //   112: ldc 101
    //   114: aload 7
    //   116: invokeinterface 97 3 0
    //   121: astore 8
    //   123: getstatic 83	com/google/android/common/base/StringUtil:ESCAPE_STRINGS	Ljava/util/Map;
    //   126: astore 9
    //   128: sipush 163
    //   131: invokestatic 89	java/lang/Character:valueOf	(C)Ljava/lang/Character;
    //   134: astore 10
    //   136: aload 9
    //   138: ldc 103
    //   140: aload 10
    //   142: invokeinterface 97 3 0
    //   147: astore 11
    //   149: getstatic 83	com/google/android/common/base/StringUtil:ESCAPE_STRINGS	Ljava/util/Map;
    //   152: astore 12
    //   154: sipush 164
    //   157: invokestatic 89	java/lang/Character:valueOf	(C)Ljava/lang/Character;
    //   160: astore 13
    //   162: aload 12
    //   164: ldc 105
    //   166: aload 13
    //   168: invokeinterface 97 3 0
    //   173: astore 14
    //   175: getstatic 83	com/google/android/common/base/StringUtil:ESCAPE_STRINGS	Ljava/util/Map;
    //   178: astore 15
    //   180: sipush 165
    //   183: invokestatic 89	java/lang/Character:valueOf	(C)Ljava/lang/Character;
    //   186: astore 16
    //   188: aload 15
    //   190: ldc 107
    //   192: aload 16
    //   194: invokeinterface 97 3 0
    //   199: astore 17
    //   201: getstatic 83	com/google/android/common/base/StringUtil:ESCAPE_STRINGS	Ljava/util/Map;
    //   204: astore 18
    //   206: sipush 166
    //   209: invokestatic 89	java/lang/Character:valueOf	(C)Ljava/lang/Character;
    //   212: astore 19
    //   214: aload 18
    //   216: ldc 109
    //   218: aload 19
    //   220: invokeinterface 97 3 0
    //   225: astore 20
    //   227: getstatic 83	com/google/android/common/base/StringUtil:ESCAPE_STRINGS	Ljava/util/Map;
    //   230: astore 21
    //   232: sipush 167
    //   235: invokestatic 89	java/lang/Character:valueOf	(C)Ljava/lang/Character;
    //   238: astore 22
    //   240: aload 21
    //   242: ldc 111
    //   244: aload 22
    //   246: invokeinterface 97 3 0
    //   251: astore 23
    //   253: getstatic 83	com/google/android/common/base/StringUtil:ESCAPE_STRINGS	Ljava/util/Map;
    //   256: astore 24
    //   258: sipush 168
    //   261: invokestatic 89	java/lang/Character:valueOf	(C)Ljava/lang/Character;
    //   264: astore 25
    //   266: aload 24
    //   268: ldc 113
    //   270: aload 25
    //   272: invokeinterface 97 3 0
    //   277: astore 26
    //   279: getstatic 83	com/google/android/common/base/StringUtil:ESCAPE_STRINGS	Ljava/util/Map;
    //   282: astore 27
    //   284: sipush 169
    //   287: invokestatic 89	java/lang/Character:valueOf	(C)Ljava/lang/Character;
    //   290: astore 28
    //   292: aload 27
    //   294: ldc 115
    //   296: aload 28
    //   298: invokeinterface 97 3 0
    //   303: astore 29
    //   305: getstatic 83	com/google/android/common/base/StringUtil:ESCAPE_STRINGS	Ljava/util/Map;
    //   308: astore 30
    //   310: sipush 170
    //   313: invokestatic 89	java/lang/Character:valueOf	(C)Ljava/lang/Character;
    //   316: astore 31
    //   318: aload 30
    //   320: ldc 117
    //   322: aload 31
    //   324: invokeinterface 97 3 0
    //   329: astore 32
    //   331: getstatic 83	com/google/android/common/base/StringUtil:ESCAPE_STRINGS	Ljava/util/Map;
    //   334: astore 33
    //   336: sipush 171
    //   339: invokestatic 89	java/lang/Character:valueOf	(C)Ljava/lang/Character;
    //   342: astore 34
    //   344: aload 33
    //   346: ldc 119
    //   348: aload 34
    //   350: invokeinterface 97 3 0
    //   355: astore 35
    //   357: getstatic 83	com/google/android/common/base/StringUtil:ESCAPE_STRINGS	Ljava/util/Map;
    //   360: astore 36
    //   362: sipush 172
    //   365: invokestatic 89	java/lang/Character:valueOf	(C)Ljava/lang/Character;
    //   368: astore 37
    //   370: aload 36
    //   372: ldc 121
    //   374: aload 37
    //   376: invokeinterface 97 3 0
    //   381: astore 38
    //   383: getstatic 83	com/google/android/common/base/StringUtil:ESCAPE_STRINGS	Ljava/util/Map;
    //   386: astore 39
    //   388: sipush 173
    //   391: invokestatic 89	java/lang/Character:valueOf	(C)Ljava/lang/Character;
    //   394: astore 40
    //   396: aload 39
    //   398: ldc 123
    //   400: aload 40
    //   402: invokeinterface 97 3 0
    //   407: astore 41
    //   409: getstatic 83	com/google/android/common/base/StringUtil:ESCAPE_STRINGS	Ljava/util/Map;
    //   412: astore 42
    //   414: sipush 174
    //   417: invokestatic 89	java/lang/Character:valueOf	(C)Ljava/lang/Character;
    //   420: astore 43
    //   422: aload 42
    //   424: ldc 125
    //   426: aload 43
    //   428: invokeinterface 97 3 0
    //   433: astore 44
    //   435: getstatic 83	com/google/android/common/base/StringUtil:ESCAPE_STRINGS	Ljava/util/Map;
    //   438: astore 45
    //   440: sipush 175
    //   443: invokestatic 89	java/lang/Character:valueOf	(C)Ljava/lang/Character;
    //   446: astore 46
    //   448: aload 45
    //   450: ldc 127
    //   452: aload 46
    //   454: invokeinterface 97 3 0
    //   459: astore 47
    //   461: getstatic 83	com/google/android/common/base/StringUtil:ESCAPE_STRINGS	Ljava/util/Map;
    //   464: astore 48
    //   466: sipush 176
    //   469: invokestatic 89	java/lang/Character:valueOf	(C)Ljava/lang/Character;
    //   472: astore 49
    //   474: aload 48
    //   476: ldc 129
    //   478: aload 49
    //   480: invokeinterface 97 3 0
    //   485: astore 50
    //   487: getstatic 83	com/google/android/common/base/StringUtil:ESCAPE_STRINGS	Ljava/util/Map;
    //   490: astore 51
    //   492: sipush 177
    //   495: invokestatic 89	java/lang/Character:valueOf	(C)Ljava/lang/Character;
    //   498: astore 52
    //   500: aload 51
    //   502: ldc 131
    //   504: aload 52
    //   506: invokeinterface 97 3 0
    //   511: astore 53
    //   513: getstatic 83	com/google/android/common/base/StringUtil:ESCAPE_STRINGS	Ljava/util/Map;
    //   516: astore 54
    //   518: sipush 178
    //   521: invokestatic 89	java/lang/Character:valueOf	(C)Ljava/lang/Character;
    //   524: astore 55
    //   526: aload 54
    //   528: ldc 133
    //   530: aload 55
    //   532: invokeinterface 97 3 0
    //   537: astore 56
    //   539: getstatic 83	com/google/android/common/base/StringUtil:ESCAPE_STRINGS	Ljava/util/Map;
    //   542: astore 57
    //   544: sipush 179
    //   547: invokestatic 89	java/lang/Character:valueOf	(C)Ljava/lang/Character;
    //   550: astore 58
    //   552: aload 57
    //   554: ldc 135
    //   556: aload 58
    //   558: invokeinterface 97 3 0
    //   563: astore 59
    //   565: getstatic 83	com/google/android/common/base/StringUtil:ESCAPE_STRINGS	Ljava/util/Map;
    //   568: astore 60
    //   570: sipush 180
    //   573: invokestatic 89	java/lang/Character:valueOf	(C)Ljava/lang/Character;
    //   576: astore 61
    //   578: aload 60
    //   580: ldc 137
    //   582: aload 61
    //   584: invokeinterface 97 3 0
    //   589: astore 62
    //   591: getstatic 83	com/google/android/common/base/StringUtil:ESCAPE_STRINGS	Ljava/util/Map;
    //   594: astore 63
    //   596: sipush 181
    //   599: invokestatic 89	java/lang/Character:valueOf	(C)Ljava/lang/Character;
    //   602: astore 64
    //   604: aload 63
    //   606: ldc 139
    //   608: aload 64
    //   610: invokeinterface 97 3 0
    //   615: astore 65
    //   617: getstatic 83	com/google/android/common/base/StringUtil:ESCAPE_STRINGS	Ljava/util/Map;
    //   620: astore 66
    //   622: sipush 182
    //   625: invokestatic 89	java/lang/Character:valueOf	(C)Ljava/lang/Character;
    //   628: astore 67
    //   630: aload 66
    //   632: ldc 141
    //   634: aload 67
    //   636: invokeinterface 97 3 0
    //   641: astore 68
    //   643: getstatic 83	com/google/android/common/base/StringUtil:ESCAPE_STRINGS	Ljava/util/Map;
    //   646: astore 69
    //   648: sipush 183
    //   651: invokestatic 89	java/lang/Character:valueOf	(C)Ljava/lang/Character;
    //   654: astore 70
    //   656: aload 69
    //   658: ldc 143
    //   660: aload 70
    //   662: invokeinterface 97 3 0
    //   667: astore 71
    //   669: getstatic 83	com/google/android/common/base/StringUtil:ESCAPE_STRINGS	Ljava/util/Map;
    //   672: astore 72
    //   674: sipush 184
    //   677: invokestatic 89	java/lang/Character:valueOf	(C)Ljava/lang/Character;
    //   680: astore 73
    //   682: aload 72
    //   684: ldc 145
    //   686: aload 73
    //   688: invokeinterface 97 3 0
    //   693: astore 74
    //   695: getstatic 83	com/google/android/common/base/StringUtil:ESCAPE_STRINGS	Ljava/util/Map;
    //   698: astore 75
    //   700: sipush 185
    //   703: invokestatic 89	java/lang/Character:valueOf	(C)Ljava/lang/Character;
    //   706: astore 76
    //   708: aload 75
    //   710: ldc 147
    //   712: aload 76
    //   714: invokeinterface 97 3 0
    //   719: astore 77
    //   721: getstatic 83	com/google/android/common/base/StringUtil:ESCAPE_STRINGS	Ljava/util/Map;
    //   724: astore 78
    //   726: sipush 186
    //   729: invokestatic 89	java/lang/Character:valueOf	(C)Ljava/lang/Character;
    //   732: astore 79
    //   734: aload 78
    //   736: ldc 149
    //   738: aload 79
    //   740: invokeinterface 97 3 0
    //   745: astore 80
    //   747: getstatic 83	com/google/android/common/base/StringUtil:ESCAPE_STRINGS	Ljava/util/Map;
    //   750: astore 81
    //   752: sipush 187
    //   755: invokestatic 89	java/lang/Character:valueOf	(C)Ljava/lang/Character;
    //   758: astore 82
    //   760: aload 81
    //   762: ldc 151
    //   764: aload 82
    //   766: invokeinterface 97 3 0
    //   771: astore 83
    //   773: getstatic 83	com/google/android/common/base/StringUtil:ESCAPE_STRINGS	Ljava/util/Map;
    //   776: astore 84
    //   778: sipush 188
    //   781: invokestatic 89	java/lang/Character:valueOf	(C)Ljava/lang/Character;
    //   784: astore 85
    //   786: aload 84
    //   788: ldc 153
    //   790: aload 85
    //   792: invokeinterface 97 3 0
    //   797: astore 86
    //   799: getstatic 83	com/google/android/common/base/StringUtil:ESCAPE_STRINGS	Ljava/util/Map;
    //   802: astore 87
    //   804: sipush 189
    //   807: invokestatic 89	java/lang/Character:valueOf	(C)Ljava/lang/Character;
    //   810: astore 88
    //   812: aload 87
    //   814: ldc 155
    //   816: aload 88
    //   818: invokeinterface 97 3 0
    //   823: astore 89
    //   825: getstatic 83	com/google/android/common/base/StringUtil:ESCAPE_STRINGS	Ljava/util/Map;
    //   828: astore 90
    //   830: sipush 190
    //   833: invokestatic 89	java/lang/Character:valueOf	(C)Ljava/lang/Character;
    //   836: astore 91
    //   838: aload 90
    //   840: ldc 157
    //   842: aload 91
    //   844: invokeinterface 97 3 0
    //   849: astore 92
    //   851: getstatic 83	com/google/android/common/base/StringUtil:ESCAPE_STRINGS	Ljava/util/Map;
    //   854: astore 93
    //   856: sipush 191
    //   859: invokestatic 89	java/lang/Character:valueOf	(C)Ljava/lang/Character;
    //   862: astore 94
    //   864: aload 93
    //   866: ldc 159
    //   868: aload 94
    //   870: invokeinterface 97 3 0
    //   875: astore 95
    //   877: getstatic 83	com/google/android/common/base/StringUtil:ESCAPE_STRINGS	Ljava/util/Map;
    //   880: astore 96
    //   882: sipush 192
    //   885: invokestatic 89	java/lang/Character:valueOf	(C)Ljava/lang/Character;
    //   888: astore 97
    //   890: aload 96
    //   892: ldc 161
    //   894: aload 97
    //   896: invokeinterface 97 3 0
    //   901: astore 98
    //   903: getstatic 83	com/google/android/common/base/StringUtil:ESCAPE_STRINGS	Ljava/util/Map;
    //   906: astore 99
    //   908: sipush 193
    //   911: invokestatic 89	java/lang/Character:valueOf	(C)Ljava/lang/Character;
    //   914: astore 100
    //   916: aload 99
    //   918: ldc 163
    //   920: aload 100
    //   922: invokeinterface 97 3 0
    //   927: astore 101
    //   929: getstatic 83	com/google/android/common/base/StringUtil:ESCAPE_STRINGS	Ljava/util/Map;
    //   932: astore 102
    //   934: sipush 194
    //   937: invokestatic 89	java/lang/Character:valueOf	(C)Ljava/lang/Character;
    //   940: astore 103
    //   942: aload 102
    //   944: ldc 165
    //   946: aload 103
    //   948: invokeinterface 97 3 0
    //   953: astore 104
    //   955: getstatic 83	com/google/android/common/base/StringUtil:ESCAPE_STRINGS	Ljava/util/Map;
    //   958: astore 105
    //   960: sipush 195
    //   963: invokestatic 89	java/lang/Character:valueOf	(C)Ljava/lang/Character;
    //   966: astore 106
    //   968: aload 105
    //   970: ldc 167
    //   972: aload 106
    //   974: invokeinterface 97 3 0
    //   979: astore 107
    //   981: getstatic 83	com/google/android/common/base/StringUtil:ESCAPE_STRINGS	Ljava/util/Map;
    //   984: astore 108
    //   986: sipush 196
    //   989: invokestatic 89	java/lang/Character:valueOf	(C)Ljava/lang/Character;
    //   992: astore 109
    //   994: aload 108
    //   996: ldc 169
    //   998: aload 109
    //   1000: invokeinterface 97 3 0
    //   1005: astore 110
    //   1007: getstatic 83	com/google/android/common/base/StringUtil:ESCAPE_STRINGS	Ljava/util/Map;
    //   1010: astore 111
    //   1012: sipush 197
    //   1015: invokestatic 89	java/lang/Character:valueOf	(C)Ljava/lang/Character;
    //   1018: astore 112
    //   1020: aload 111
    //   1022: ldc 171
    //   1024: aload 112
    //   1026: invokeinterface 97 3 0
    //   1031: astore 113
    //   1033: getstatic 83	com/google/android/common/base/StringUtil:ESCAPE_STRINGS	Ljava/util/Map;
    //   1036: astore 114
    //   1038: sipush 198
    //   1041: invokestatic 89	java/lang/Character:valueOf	(C)Ljava/lang/Character;
    //   1044: astore 115
    //   1046: aload 114
    //   1048: ldc 173
    //   1050: aload 115
    //   1052: invokeinterface 97 3 0
    //   1057: astore 116
    //   1059: getstatic 83	com/google/android/common/base/StringUtil:ESCAPE_STRINGS	Ljava/util/Map;
    //   1062: astore 117
    //   1064: sipush 199
    //   1067: invokestatic 89	java/lang/Character:valueOf	(C)Ljava/lang/Character;
    //   1070: astore 118
    //   1072: aload 117
    //   1074: ldc 175
    //   1076: aload 118
    //   1078: invokeinterface 97 3 0
    //   1083: astore 119
    //   1085: getstatic 83	com/google/android/common/base/StringUtil:ESCAPE_STRINGS	Ljava/util/Map;
    //   1088: astore 120
    //   1090: sipush 200
    //   1093: invokestatic 89	java/lang/Character:valueOf	(C)Ljava/lang/Character;
    //   1096: astore 121
    //   1098: aload 120
    //   1100: ldc 177
    //   1102: aload 121
    //   1104: invokeinterface 97 3 0
    //   1109: astore 122
    //   1111: getstatic 83	com/google/android/common/base/StringUtil:ESCAPE_STRINGS	Ljava/util/Map;
    //   1114: astore 123
    //   1116: sipush 201
    //   1119: invokestatic 89	java/lang/Character:valueOf	(C)Ljava/lang/Character;
    //   1122: astore 124
    //   1124: aload 123
    //   1126: ldc 179
    //   1128: aload 124
    //   1130: invokeinterface 97 3 0
    //   1135: astore 125
    //   1137: getstatic 83	com/google/android/common/base/StringUtil:ESCAPE_STRINGS	Ljava/util/Map;
    //   1140: astore 126
    //   1142: sipush 202
    //   1145: invokestatic 89	java/lang/Character:valueOf	(C)Ljava/lang/Character;
    //   1148: astore 127
    //   1150: aload 126
    //   1152: ldc 181
    //   1154: aload 127
    //   1156: invokeinterface 97 3 0
    //   1161: astore 128
    //   1163: getstatic 83	com/google/android/common/base/StringUtil:ESCAPE_STRINGS	Ljava/util/Map;
    //   1166: astore 129
    //   1168: sipush 203
    //   1171: invokestatic 89	java/lang/Character:valueOf	(C)Ljava/lang/Character;
    //   1174: astore 130
    //   1176: aload 129
    //   1178: ldc 183
    //   1180: aload 130
    //   1182: invokeinterface 97 3 0
    //   1187: astore 131
    //   1189: getstatic 83	com/google/android/common/base/StringUtil:ESCAPE_STRINGS	Ljava/util/Map;
    //   1192: astore 132
    //   1194: sipush 204
    //   1197: invokestatic 89	java/lang/Character:valueOf	(C)Ljava/lang/Character;
    //   1200: astore 133
    //   1202: aload 132
    //   1204: ldc 185
    //   1206: aload 133
    //   1208: invokeinterface 97 3 0
    //   1213: astore 134
    //   1215: getstatic 83	com/google/android/common/base/StringUtil:ESCAPE_STRINGS	Ljava/util/Map;
    //   1218: astore 135
    //   1220: sipush 205
    //   1223: invokestatic 89	java/lang/Character:valueOf	(C)Ljava/lang/Character;
    //   1226: astore 136
    //   1228: aload 135
    //   1230: ldc 187
    //   1232: aload 136
    //   1234: invokeinterface 97 3 0
    //   1239: astore 137
    //   1241: getstatic 83	com/google/android/common/base/StringUtil:ESCAPE_STRINGS	Ljava/util/Map;
    //   1244: astore 138
    //   1246: sipush 206
    //   1249: invokestatic 89	java/lang/Character:valueOf	(C)Ljava/lang/Character;
    //   1252: astore 139
    //   1254: aload 138
    //   1256: ldc 189
    //   1258: aload 139
    //   1260: invokeinterface 97 3 0
    //   1265: astore 140
    //   1267: getstatic 83	com/google/android/common/base/StringUtil:ESCAPE_STRINGS	Ljava/util/Map;
    //   1270: astore 141
    //   1272: sipush 207
    //   1275: invokestatic 89	java/lang/Character:valueOf	(C)Ljava/lang/Character;
    //   1278: astore 142
    //   1280: aload 141
    //   1282: ldc 191
    //   1284: aload 142
    //   1286: invokeinterface 97 3 0
    //   1291: astore 143
    //   1293: getstatic 83	com/google/android/common/base/StringUtil:ESCAPE_STRINGS	Ljava/util/Map;
    //   1296: astore 144
    //   1298: sipush 208
    //   1301: invokestatic 89	java/lang/Character:valueOf	(C)Ljava/lang/Character;
    //   1304: astore 145
    //   1306: aload 144
    //   1308: ldc 193
    //   1310: aload 145
    //   1312: invokeinterface 97 3 0
    //   1317: astore 146
    //   1319: getstatic 83	com/google/android/common/base/StringUtil:ESCAPE_STRINGS	Ljava/util/Map;
    //   1322: astore 147
    //   1324: sipush 209
    //   1327: invokestatic 89	java/lang/Character:valueOf	(C)Ljava/lang/Character;
    //   1330: astore 148
    //   1332: aload 147
    //   1334: ldc 195
    //   1336: aload 148
    //   1338: invokeinterface 97 3 0
    //   1343: astore 149
    //   1345: getstatic 83	com/google/android/common/base/StringUtil:ESCAPE_STRINGS	Ljava/util/Map;
    //   1348: astore 150
    //   1350: sipush 210
    //   1353: invokestatic 89	java/lang/Character:valueOf	(C)Ljava/lang/Character;
    //   1356: astore 151
    //   1358: aload 150
    //   1360: ldc 197
    //   1362: aload 151
    //   1364: invokeinterface 97 3 0
    //   1369: astore 152
    //   1371: getstatic 83	com/google/android/common/base/StringUtil:ESCAPE_STRINGS	Ljava/util/Map;
    //   1374: astore 153
    //   1376: sipush 211
    //   1379: invokestatic 89	java/lang/Character:valueOf	(C)Ljava/lang/Character;
    //   1382: astore 154
    //   1384: aload 153
    //   1386: ldc 199
    //   1388: aload 154
    //   1390: invokeinterface 97 3 0
    //   1395: astore 155
    //   1397: getstatic 83	com/google/android/common/base/StringUtil:ESCAPE_STRINGS	Ljava/util/Map;
    //   1400: astore 156
    //   1402: sipush 212
    //   1405: invokestatic 89	java/lang/Character:valueOf	(C)Ljava/lang/Character;
    //   1408: astore 157
    //   1410: aload 156
    //   1412: ldc 201
    //   1414: aload 157
    //   1416: invokeinterface 97 3 0
    //   1421: astore 158
    //   1423: getstatic 83	com/google/android/common/base/StringUtil:ESCAPE_STRINGS	Ljava/util/Map;
    //   1426: astore 159
    //   1428: sipush 213
    //   1431: invokestatic 89	java/lang/Character:valueOf	(C)Ljava/lang/Character;
    //   1434: astore 160
    //   1436: aload 159
    //   1438: ldc 203
    //   1440: aload 160
    //   1442: invokeinterface 97 3 0
    //   1447: astore 161
    //   1449: getstatic 83	com/google/android/common/base/StringUtil:ESCAPE_STRINGS	Ljava/util/Map;
    //   1452: astore 162
    //   1454: sipush 214
    //   1457: invokestatic 89	java/lang/Character:valueOf	(C)Ljava/lang/Character;
    //   1460: astore 163
    //   1462: aload 162
    //   1464: ldc 205
    //   1466: aload 163
    //   1468: invokeinterface 97 3 0
    //   1473: astore 164
    //   1475: getstatic 83	com/google/android/common/base/StringUtil:ESCAPE_STRINGS	Ljava/util/Map;
    //   1478: astore 165
    //   1480: sipush 215
    //   1483: invokestatic 89	java/lang/Character:valueOf	(C)Ljava/lang/Character;
    //   1486: astore 166
    //   1488: aload 165
    //   1490: ldc 207
    //   1492: aload 166
    //   1494: invokeinterface 97 3 0
    //   1499: astore 167
    //   1501: getstatic 83	com/google/android/common/base/StringUtil:ESCAPE_STRINGS	Ljava/util/Map;
    //   1504: astore 168
    //   1506: sipush 216
    //   1509: invokestatic 89	java/lang/Character:valueOf	(C)Ljava/lang/Character;
    //   1512: astore 169
    //   1514: aload 168
    //   1516: ldc 209
    //   1518: aload 169
    //   1520: invokeinterface 97 3 0
    //   1525: astore 170
    //   1527: getstatic 83	com/google/android/common/base/StringUtil:ESCAPE_STRINGS	Ljava/util/Map;
    //   1530: astore 171
    //   1532: sipush 217
    //   1535: invokestatic 89	java/lang/Character:valueOf	(C)Ljava/lang/Character;
    //   1538: astore 172
    //   1540: aload 171
    //   1542: ldc 211
    //   1544: aload 172
    //   1546: invokeinterface 97 3 0
    //   1551: astore 173
    //   1553: getstatic 83	com/google/android/common/base/StringUtil:ESCAPE_STRINGS	Ljava/util/Map;
    //   1556: astore 174
    //   1558: sipush 218
    //   1561: invokestatic 89	java/lang/Character:valueOf	(C)Ljava/lang/Character;
    //   1564: astore 175
    //   1566: aload 174
    //   1568: ldc 213
    //   1570: aload 175
    //   1572: invokeinterface 97 3 0
    //   1577: astore 176
    //   1579: getstatic 83	com/google/android/common/base/StringUtil:ESCAPE_STRINGS	Ljava/util/Map;
    //   1582: astore 177
    //   1584: sipush 219
    //   1587: invokestatic 89	java/lang/Character:valueOf	(C)Ljava/lang/Character;
    //   1590: astore 178
    //   1592: aload 177
    //   1594: ldc 215
    //   1596: aload 178
    //   1598: invokeinterface 97 3 0
    //   1603: astore 179
    //   1605: getstatic 83	com/google/android/common/base/StringUtil:ESCAPE_STRINGS	Ljava/util/Map;
    //   1608: astore 180
    //   1610: sipush 220
    //   1613: invokestatic 89	java/lang/Character:valueOf	(C)Ljava/lang/Character;
    //   1616: astore 181
    //   1618: aload 180
    //   1620: ldc 217
    //   1622: aload 181
    //   1624: invokeinterface 97 3 0
    //   1629: astore 182
    //   1631: getstatic 83	com/google/android/common/base/StringUtil:ESCAPE_STRINGS	Ljava/util/Map;
    //   1634: astore 183
    //   1636: sipush 221
    //   1639: invokestatic 89	java/lang/Character:valueOf	(C)Ljava/lang/Character;
    //   1642: astore 184
    //   1644: aload 183
    //   1646: ldc 219
    //   1648: aload 184
    //   1650: invokeinterface 97 3 0
    //   1655: astore 185
    //   1657: getstatic 83	com/google/android/common/base/StringUtil:ESCAPE_STRINGS	Ljava/util/Map;
    //   1660: astore 186
    //   1662: sipush 222
    //   1665: invokestatic 89	java/lang/Character:valueOf	(C)Ljava/lang/Character;
    //   1668: astore 187
    //   1670: aload 186
    //   1672: ldc 221
    //   1674: aload 187
    //   1676: invokeinterface 97 3 0
    //   1681: astore 188
    //   1683: getstatic 83	com/google/android/common/base/StringUtil:ESCAPE_STRINGS	Ljava/util/Map;
    //   1686: astore 189
    //   1688: sipush 223
    //   1691: invokestatic 89	java/lang/Character:valueOf	(C)Ljava/lang/Character;
    //   1694: astore 190
    //   1696: aload 189
    //   1698: ldc 223
    //   1700: aload 190
    //   1702: invokeinterface 97 3 0
    //   1707: astore 191
    //   1709: getstatic 83	com/google/android/common/base/StringUtil:ESCAPE_STRINGS	Ljava/util/Map;
    //   1712: astore 192
    //   1714: sipush 224
    //   1717: invokestatic 89	java/lang/Character:valueOf	(C)Ljava/lang/Character;
    //   1720: astore 193
    //   1722: aload 192
    //   1724: ldc 225
    //   1726: aload 193
    //   1728: invokeinterface 97 3 0
    //   1733: astore 194
    //   1735: getstatic 83	com/google/android/common/base/StringUtil:ESCAPE_STRINGS	Ljava/util/Map;
    //   1738: astore 195
    //   1740: sipush 225
    //   1743: invokestatic 89	java/lang/Character:valueOf	(C)Ljava/lang/Character;
    //   1746: astore 196
    //   1748: aload 195
    //   1750: ldc 227
    //   1752: aload 196
    //   1754: invokeinterface 97 3 0
    //   1759: astore 197
    //   1761: getstatic 83	com/google/android/common/base/StringUtil:ESCAPE_STRINGS	Ljava/util/Map;
    //   1764: astore 198
    //   1766: sipush 226
    //   1769: invokestatic 89	java/lang/Character:valueOf	(C)Ljava/lang/Character;
    //   1772: astore 199
    //   1774: aload 198
    //   1776: ldc 229
    //   1778: aload 199
    //   1780: invokeinterface 97 3 0
    //   1785: astore 200
    //   1787: getstatic 83	com/google/android/common/base/StringUtil:ESCAPE_STRINGS	Ljava/util/Map;
    //   1790: astore 201
    //   1792: sipush 227
    //   1795: invokestatic 89	java/lang/Character:valueOf	(C)Ljava/lang/Character;
    //   1798: astore 202
    //   1800: aload 201
    //   1802: ldc 231
    //   1804: aload 202
    //   1806: invokeinterface 97 3 0
    //   1811: astore 203
    //   1813: getstatic 83	com/google/android/common/base/StringUtil:ESCAPE_STRINGS	Ljava/util/Map;
    //   1816: astore 204
    //   1818: sipush 228
    //   1821: invokestatic 89	java/lang/Character:valueOf	(C)Ljava/lang/Character;
    //   1824: astore 205
    //   1826: aload 204
    //   1828: ldc 233
    //   1830: aload 205
    //   1832: invokeinterface 97 3 0
    //   1837: astore 206
    //   1839: getstatic 83	com/google/android/common/base/StringUtil:ESCAPE_STRINGS	Ljava/util/Map;
    //   1842: astore 207
    //   1844: sipush 229
    //   1847: invokestatic 89	java/lang/Character:valueOf	(C)Ljava/lang/Character;
    //   1850: astore 208
    //   1852: aload 207
    //   1854: ldc 235
    //   1856: aload 208
    //   1858: invokeinterface 97 3 0
    //   1863: astore 209
    //   1865: getstatic 83	com/google/android/common/base/StringUtil:ESCAPE_STRINGS	Ljava/util/Map;
    //   1868: astore 210
    //   1870: sipush 230
    //   1873: invokestatic 89	java/lang/Character:valueOf	(C)Ljava/lang/Character;
    //   1876: astore 211
    //   1878: aload 210
    //   1880: ldc 237
    //   1882: aload 211
    //   1884: invokeinterface 97 3 0
    //   1889: astore 212
    //   1891: getstatic 83	com/google/android/common/base/StringUtil:ESCAPE_STRINGS	Ljava/util/Map;
    //   1894: astore 213
    //   1896: sipush 231
    //   1899: invokestatic 89	java/lang/Character:valueOf	(C)Ljava/lang/Character;
    //   1902: astore 214
    //   1904: aload 213
    //   1906: ldc 239
    //   1908: aload 214
    //   1910: invokeinterface 97 3 0
    //   1915: astore 215
    //   1917: getstatic 83	com/google/android/common/base/StringUtil:ESCAPE_STRINGS	Ljava/util/Map;
    //   1920: astore 216
    //   1922: sipush 232
    //   1925: invokestatic 89	java/lang/Character:valueOf	(C)Ljava/lang/Character;
    //   1928: astore 217
    //   1930: aload 216
    //   1932: ldc 241
    //   1934: aload 217
    //   1936: invokeinterface 97 3 0
    //   1941: astore 218
    //   1943: getstatic 83	com/google/android/common/base/StringUtil:ESCAPE_STRINGS	Ljava/util/Map;
    //   1946: astore 219
    //   1948: sipush 233
    //   1951: invokestatic 89	java/lang/Character:valueOf	(C)Ljava/lang/Character;
    //   1954: astore 220
    //   1956: aload 219
    //   1958: ldc 243
    //   1960: aload 220
    //   1962: invokeinterface 97 3 0
    //   1967: astore 221
    //   1969: getstatic 83	com/google/android/common/base/StringUtil:ESCAPE_STRINGS	Ljava/util/Map;
    //   1972: astore 222
    //   1974: sipush 234
    //   1977: invokestatic 89	java/lang/Character:valueOf	(C)Ljava/lang/Character;
    //   1980: astore 223
    //   1982: aload 222
    //   1984: ldc 245
    //   1986: aload 223
    //   1988: invokeinterface 97 3 0
    //   1993: astore 224
    //   1995: getstatic 83	com/google/android/common/base/StringUtil:ESCAPE_STRINGS	Ljava/util/Map;
    //   1998: astore 225
    //   2000: sipush 235
    //   2003: invokestatic 89	java/lang/Character:valueOf	(C)Ljava/lang/Character;
    //   2006: astore 226
    //   2008: aload 225
    //   2010: ldc 247
    //   2012: aload 226
    //   2014: invokeinterface 97 3 0
    //   2019: astore 227
    //   2021: getstatic 83	com/google/android/common/base/StringUtil:ESCAPE_STRINGS	Ljava/util/Map;
    //   2024: astore 228
    //   2026: sipush 236
    //   2029: invokestatic 89	java/lang/Character:valueOf	(C)Ljava/lang/Character;
    //   2032: astore 229
    //   2034: aload 228
    //   2036: ldc 249
    //   2038: aload 229
    //   2040: invokeinterface 97 3 0
    //   2045: astore 230
    //   2047: getstatic 83	com/google/android/common/base/StringUtil:ESCAPE_STRINGS	Ljava/util/Map;
    //   2050: astore 231
    //   2052: sipush 237
    //   2055: invokestatic 89	java/lang/Character:valueOf	(C)Ljava/lang/Character;
    //   2058: astore 232
    //   2060: aload 231
    //   2062: ldc 251
    //   2064: aload 232
    //   2066: invokeinterface 97 3 0
    //   2071: astore 233
    //   2073: getstatic 83	com/google/android/common/base/StringUtil:ESCAPE_STRINGS	Ljava/util/Map;
    //   2076: astore 234
    //   2078: sipush 238
    //   2081: invokestatic 89	java/lang/Character:valueOf	(C)Ljava/lang/Character;
    //   2084: astore 235
    //   2086: aload 234
    //   2088: ldc 253
    //   2090: aload 235
    //   2092: invokeinterface 97 3 0
    //   2097: astore 236
    //   2099: getstatic 83	com/google/android/common/base/StringUtil:ESCAPE_STRINGS	Ljava/util/Map;
    //   2102: astore 237
    //   2104: sipush 239
    //   2107: invokestatic 89	java/lang/Character:valueOf	(C)Ljava/lang/Character;
    //   2110: astore 238
    //   2112: aload 237
    //   2114: ldc 255
    //   2116: aload 238
    //   2118: invokeinterface 97 3 0
    //   2123: astore 239
    //   2125: getstatic 83	com/google/android/common/base/StringUtil:ESCAPE_STRINGS	Ljava/util/Map;
    //   2128: astore 240
    //   2130: sipush 240
    //   2133: invokestatic 89	java/lang/Character:valueOf	(C)Ljava/lang/Character;
    //   2136: astore 241
    //   2138: aload 240
    //   2140: ldc_w 257
    //   2143: aload 241
    //   2145: invokeinterface 97 3 0
    //   2150: astore 242
    //   2152: getstatic 83	com/google/android/common/base/StringUtil:ESCAPE_STRINGS	Ljava/util/Map;
    //   2155: astore 243
    //   2157: sipush 241
    //   2160: invokestatic 89	java/lang/Character:valueOf	(C)Ljava/lang/Character;
    //   2163: astore 244
    //   2165: aload 243
    //   2167: ldc_w 259
    //   2170: aload 244
    //   2172: invokeinterface 97 3 0
    //   2177: astore 245
    //   2179: getstatic 83	com/google/android/common/base/StringUtil:ESCAPE_STRINGS	Ljava/util/Map;
    //   2182: astore 246
    //   2184: sipush 242
    //   2187: invokestatic 89	java/lang/Character:valueOf	(C)Ljava/lang/Character;
    //   2190: astore 247
    //   2192: aload 246
    //   2194: ldc_w 261
    //   2197: aload 247
    //   2199: invokeinterface 97 3 0
    //   2204: astore 248
    //   2206: getstatic 83	com/google/android/common/base/StringUtil:ESCAPE_STRINGS	Ljava/util/Map;
    //   2209: astore 249
    //   2211: sipush 243
    //   2214: invokestatic 89	java/lang/Character:valueOf	(C)Ljava/lang/Character;
    //   2217: astore 250
    //   2219: aload 249
    //   2221: ldc_w 263
    //   2224: aload 250
    //   2226: invokeinterface 97 3 0
    //   2231: astore 251
    //   2233: getstatic 83	com/google/android/common/base/StringUtil:ESCAPE_STRINGS	Ljava/util/Map;
    //   2236: astore 252
    //   2238: sipush 244
    //   2241: invokestatic 89	java/lang/Character:valueOf	(C)Ljava/lang/Character;
    //   2244: astore 253
    //   2246: aload 252
    //   2248: ldc_w 265
    //   2251: aload 253
    //   2253: invokeinterface 97 3 0
    //   2258: astore 254
    //   2260: getstatic 83	com/google/android/common/base/StringUtil:ESCAPE_STRINGS	Ljava/util/Map;
    //   2263: astore 255
    //   2265: sipush 245
    //   2268: invokestatic 89	java/lang/Character:valueOf	(C)Ljava/lang/Character;
    //   2271: wide
    //   2275: aload 255
    //   2277: ldc_w 267
    //   2280: wide
    //   2284: invokeinterface 97 3 0
    //   2289: wide
    //   2293: getstatic 83	com/google/android/common/base/StringUtil:ESCAPE_STRINGS	Ljava/util/Map;
    //   2296: wide
    //   2300: sipush 246
    //   2303: invokestatic 89	java/lang/Character:valueOf	(C)Ljava/lang/Character;
    //   2306: wide
    //   2310: wide
    //   2314: ldc_w 269
    //   2317: wide
    //   2321: invokeinterface 97 3 0
    //   2326: wide
    //   2330: getstatic 83	com/google/android/common/base/StringUtil:ESCAPE_STRINGS	Ljava/util/Map;
    //   2333: wide
    //   2337: sipush 247
    //   2340: invokestatic 89	java/lang/Character:valueOf	(C)Ljava/lang/Character;
    //   2343: wide
    //   2347: wide
    //   2351: ldc_w 271
    //   2354: wide
    //   2358: invokeinterface 97 3 0
    //   2363: wide
    //   2367: getstatic 83	com/google/android/common/base/StringUtil:ESCAPE_STRINGS	Ljava/util/Map;
    //   2370: wide
    //   2374: sipush 248
    //   2377: invokestatic 89	java/lang/Character:valueOf	(C)Ljava/lang/Character;
    //   2380: wide
    //   2384: wide
    //   2388: ldc_w 273
    //   2391: wide
    //   2395: invokeinterface 97 3 0
    //   2400: wide
    //   2404: getstatic 83	com/google/android/common/base/StringUtil:ESCAPE_STRINGS	Ljava/util/Map;
    //   2407: wide
    //   2411: sipush 249
    //   2414: invokestatic 89	java/lang/Character:valueOf	(C)Ljava/lang/Character;
    //   2417: wide
    //   2421: wide
    //   2425: ldc_w 275
    //   2428: wide
    //   2432: invokeinterface 97 3 0
    //   2437: wide
    //   2441: getstatic 83	com/google/android/common/base/StringUtil:ESCAPE_STRINGS	Ljava/util/Map;
    //   2444: wide
    //   2448: sipush 250
    //   2451: invokestatic 89	java/lang/Character:valueOf	(C)Ljava/lang/Character;
    //   2454: wide
    //   2458: wide
    //   2462: ldc_w 277
    //   2465: wide
    //   2469: invokeinterface 97 3 0
    //   2474: wide
    //   2478: getstatic 83	com/google/android/common/base/StringUtil:ESCAPE_STRINGS	Ljava/util/Map;
    //   2481: wide
    //   2485: sipush 251
    //   2488: invokestatic 89	java/lang/Character:valueOf	(C)Ljava/lang/Character;
    //   2491: wide
    //   2495: wide
    //   2499: ldc_w 279
    //   2502: wide
    //   2506: invokeinterface 97 3 0
    //   2511: wide
    //   2515: getstatic 83	com/google/android/common/base/StringUtil:ESCAPE_STRINGS	Ljava/util/Map;
    //   2518: wide
    //   2522: sipush 252
    //   2525: invokestatic 89	java/lang/Character:valueOf	(C)Ljava/lang/Character;
    //   2528: wide
    //   2532: wide
    //   2536: ldc_w 281
    //   2539: wide
    //   2543: invokeinterface 97 3 0
    //   2548: wide
    //   2552: getstatic 83	com/google/android/common/base/StringUtil:ESCAPE_STRINGS	Ljava/util/Map;
    //   2555: wide
    //   2559: sipush 253
    //   2562: invokestatic 89	java/lang/Character:valueOf	(C)Ljava/lang/Character;
    //   2565: wide
    //   2569: wide
    //   2573: ldc_w 283
    //   2576: wide
    //   2580: invokeinterface 97 3 0
    //   2585: wide
    //   2589: getstatic 83	com/google/android/common/base/StringUtil:ESCAPE_STRINGS	Ljava/util/Map;
    //   2592: wide
    //   2596: sipush 254
    //   2599: invokestatic 89	java/lang/Character:valueOf	(C)Ljava/lang/Character;
    //   2602: wide
    //   2606: wide
    //   2610: ldc_w 285
    //   2613: wide
    //   2617: invokeinterface 97 3 0
    //   2622: wide
    //   2626: getstatic 83	com/google/android/common/base/StringUtil:ESCAPE_STRINGS	Ljava/util/Map;
    //   2629: wide
    //   2633: sipush 255
    //   2636: invokestatic 89	java/lang/Character:valueOf	(C)Ljava/lang/Character;
    //   2639: wide
    //   2643: wide
    //   2647: ldc_w 287
    //   2650: wide
    //   2654: invokeinterface 97 3 0
    //   2659: wide
    //   2663: getstatic 83	com/google/android/common/base/StringUtil:ESCAPE_STRINGS	Ljava/util/Map;
    //   2666: wide
    //   2670: sipush 402
    //   2673: invokestatic 89	java/lang/Character:valueOf	(C)Ljava/lang/Character;
    //   2676: wide
    //   2680: wide
    //   2684: ldc_w 289
    //   2687: wide
    //   2691: invokeinterface 97 3 0
    //   2696: wide
    //   2700: getstatic 83	com/google/android/common/base/StringUtil:ESCAPE_STRINGS	Ljava/util/Map;
    //   2703: wide
    //   2707: sipush 913
    //   2710: invokestatic 89	java/lang/Character:valueOf	(C)Ljava/lang/Character;
    //   2713: wide
    //   2717: wide
    //   2721: ldc_w 291
    //   2724: wide
    //   2728: invokeinterface 97 3 0
    //   2733: wide
    //   2737: getstatic 83	com/google/android/common/base/StringUtil:ESCAPE_STRINGS	Ljava/util/Map;
    //   2740: wide
    //   2744: sipush 914
    //   2747: invokestatic 89	java/lang/Character:valueOf	(C)Ljava/lang/Character;
    //   2750: wide
    //   2754: wide
    //   2758: ldc_w 293
    //   2761: wide
    //   2765: invokeinterface 97 3 0
    //   2770: wide
    //   2774: getstatic 83	com/google/android/common/base/StringUtil:ESCAPE_STRINGS	Ljava/util/Map;
    //   2777: wide
    //   2781: sipush 915
    //   2784: invokestatic 89	java/lang/Character:valueOf	(C)Ljava/lang/Character;
    //   2787: wide
    //   2791: wide
    //   2795: ldc_w 295
    //   2798: wide
    //   2802: invokeinterface 97 3 0
    //   2807: wide
    //   2811: getstatic 83	com/google/android/common/base/StringUtil:ESCAPE_STRINGS	Ljava/util/Map;
    //   2814: wide
    //   2818: sipush 916
    //   2821: invokestatic 89	java/lang/Character:valueOf	(C)Ljava/lang/Character;
    //   2824: wide
    //   2828: wide
    //   2832: ldc_w 297
    //   2835: wide
    //   2839: invokeinterface 97 3 0
    //   2844: wide
    //   2848: getstatic 83	com/google/android/common/base/StringUtil:ESCAPE_STRINGS	Ljava/util/Map;
    //   2851: wide
    //   2855: sipush 917
    //   2858: invokestatic 89	java/lang/Character:valueOf	(C)Ljava/lang/Character;
    //   2861: wide
    //   2865: wide
    //   2869: ldc_w 299
    //   2872: wide
    //   2876: invokeinterface 97 3 0
    //   2881: wide
    //   2885: getstatic 83	com/google/android/common/base/StringUtil:ESCAPE_STRINGS	Ljava/util/Map;
    //   2888: wide
    //   2892: sipush 918
    //   2895: invokestatic 89	java/lang/Character:valueOf	(C)Ljava/lang/Character;
    //   2898: wide
    //   2902: wide
    //   2906: ldc_w 301
    //   2909: wide
    //   2913: invokeinterface 97 3 0
    //   2918: wide
    //   2922: getstatic 83	com/google/android/common/base/StringUtil:ESCAPE_STRINGS	Ljava/util/Map;
    //   2925: wide
    //   2929: sipush 919
    //   2932: invokestatic 89	java/lang/Character:valueOf	(C)Ljava/lang/Character;
    //   2935: wide
    //   2939: wide
    //   2943: ldc_w 303
    //   2946: wide
    //   2950: invokeinterface 97 3 0
    //   2955: wide
    //   2959: getstatic 83	com/google/android/common/base/StringUtil:ESCAPE_STRINGS	Ljava/util/Map;
    //   2962: wide
    //   2966: sipush 920
    //   2969: invokestatic 89	java/lang/Character:valueOf	(C)Ljava/lang/Character;
    //   2972: wide
    //   2976: wide
    //   2980: ldc_w 305
    //   2983: wide
    //   2987: invokeinterface 97 3 0
    //   2992: wide
    //   2996: getstatic 83	com/google/android/common/base/StringUtil:ESCAPE_STRINGS	Ljava/util/Map;
    //   2999: wide
    //   3003: sipush 921
    //   3006: invokestatic 89	java/lang/Character:valueOf	(C)Ljava/lang/Character;
    //   3009: wide
    //   3013: wide
    //   3017: ldc_w 307
    //   3020: wide
    //   3024: invokeinterface 97 3 0
    //   3029: wide
    //   3033: getstatic 83	com/google/android/common/base/StringUtil:ESCAPE_STRINGS	Ljava/util/Map;
    //   3036: wide
    //   3040: sipush 922
    //   3043: invokestatic 89	java/lang/Character:valueOf	(C)Ljava/lang/Character;
    //   3046: wide
    //   3050: wide
    //   3054: ldc_w 309
    //   3057: wide
    //   3061: invokeinterface 97 3 0
    //   3066: wide
    //   3070: getstatic 83	com/google/android/common/base/StringUtil:ESCAPE_STRINGS	Ljava/util/Map;
    //   3073: wide
    //   3077: sipush 923
    //   3080: invokestatic 89	java/lang/Character:valueOf	(C)Ljava/lang/Character;
    //   3083: wide
    //   3087: wide
    //   3091: ldc_w 311
    //   3094: wide
    //   3098: invokeinterface 97 3 0
    //   3103: wide
    //   3107: getstatic 83	com/google/android/common/base/StringUtil:ESCAPE_STRINGS	Ljava/util/Map;
    //   3110: wide
    //   3114: sipush 924
    //   3117: invokestatic 89	java/lang/Character:valueOf	(C)Ljava/lang/Character;
    //   3120: wide
    //   3124: wide
    //   3128: ldc_w 313
    //   3131: wide
    //   3135: invokeinterface 97 3 0
    //   3140: wide
    //   3144: getstatic 83	com/google/android/common/base/StringUtil:ESCAPE_STRINGS	Ljava/util/Map;
    //   3147: wide
    //   3151: sipush 925
    //   3154: invokestatic 89	java/lang/Character:valueOf	(C)Ljava/lang/Character;
    //   3157: wide
    //   3161: wide
    //   3165: ldc_w 315
    //   3168: wide
    //   3172: invokeinterface 97 3 0
    //   3177: wide
    //   3181: getstatic 83	com/google/android/common/base/StringUtil:ESCAPE_STRINGS	Ljava/util/Map;
    //   3184: wide
    //   3188: sipush 926
    //   3191: invokestatic 89	java/lang/Character:valueOf	(C)Ljava/lang/Character;
    //   3194: wide
    //   3198: wide
    //   3202: ldc_w 317
    //   3205: wide
    //   3209: invokeinterface 97 3 0
    //   3214: wide
    //   3218: getstatic 83	com/google/android/common/base/StringUtil:ESCAPE_STRINGS	Ljava/util/Map;
    //   3221: wide
    //   3225: sipush 927
    //   3228: invokestatic 89	java/lang/Character:valueOf	(C)Ljava/lang/Character;
    //   3231: wide
    //   3235: wide
    //   3239: ldc_w 319
    //   3242: wide
    //   3246: invokeinterface 97 3 0
    //   3251: wide
    //   3255: getstatic 83	com/google/android/common/base/StringUtil:ESCAPE_STRINGS	Ljava/util/Map;
    //   3258: wide
    //   3262: sipush 928
    //   3265: invokestatic 89	java/lang/Character:valueOf	(C)Ljava/lang/Character;
    //   3268: wide
    //   3272: wide
    //   3276: ldc_w 321
    //   3279: wide
    //   3283: invokeinterface 97 3 0
    //   3288: wide
    //   3292: getstatic 83	com/google/android/common/base/StringUtil:ESCAPE_STRINGS	Ljava/util/Map;
    //   3295: wide
    //   3299: sipush 929
    //   3302: invokestatic 89	java/lang/Character:valueOf	(C)Ljava/lang/Character;
    //   3305: wide
    //   3309: wide
    //   3313: ldc_w 323
    //   3316: wide
    //   3320: invokeinterface 97 3 0
    //   3325: wide
    //   3329: getstatic 83	com/google/android/common/base/StringUtil:ESCAPE_STRINGS	Ljava/util/Map;
    //   3332: wide
    //   3336: sipush 931
    //   3339: invokestatic 89	java/lang/Character:valueOf	(C)Ljava/lang/Character;
    //   3342: wide
    //   3346: wide
    //   3350: ldc_w 325
    //   3353: wide
    //   3357: invokeinterface 97 3 0
    //   3362: wide
    //   3366: getstatic 83	com/google/android/common/base/StringUtil:ESCAPE_STRINGS	Ljava/util/Map;
    //   3369: wide
    //   3373: sipush 932
    //   3376: invokestatic 89	java/lang/Character:valueOf	(C)Ljava/lang/Character;
    //   3379: wide
    //   3383: wide
    //   3387: ldc_w 327
    //   3390: wide
    //   3394: invokeinterface 97 3 0
    //   3399: wide
    //   3403: getstatic 83	com/google/android/common/base/StringUtil:ESCAPE_STRINGS	Ljava/util/Map;
    //   3406: wide
    //   3410: sipush 933
    //   3413: invokestatic 89	java/lang/Character:valueOf	(C)Ljava/lang/Character;
    //   3416: wide
    //   3420: wide
    //   3424: ldc_w 329
    //   3427: wide
    //   3431: invokeinterface 97 3 0
    //   3436: wide
    //   3440: getstatic 83	com/google/android/common/base/StringUtil:ESCAPE_STRINGS	Ljava/util/Map;
    //   3443: wide
    //   3447: sipush 934
    //   3450: invokestatic 89	java/lang/Character:valueOf	(C)Ljava/lang/Character;
    //   3453: wide
    //   3457: wide
    //   3461: ldc_w 331
    //   3464: wide
    //   3468: invokeinterface 97 3 0
    //   3473: wide
    //   3477: getstatic 83	com/google/android/common/base/StringUtil:ESCAPE_STRINGS	Ljava/util/Map;
    //   3480: wide
    //   3484: sipush 935
    //   3487: invokestatic 89	java/lang/Character:valueOf	(C)Ljava/lang/Character;
    //   3490: wide
    //   3494: wide
    //   3498: ldc_w 333
    //   3501: wide
    //   3505: invokeinterface 97 3 0
    //   3510: wide
    //   3514: getstatic 83	com/google/android/common/base/StringUtil:ESCAPE_STRINGS	Ljava/util/Map;
    //   3517: wide
    //   3521: sipush 936
    //   3524: invokestatic 89	java/lang/Character:valueOf	(C)Ljava/lang/Character;
    //   3527: wide
    //   3531: wide
    //   3535: ldc_w 335
    //   3538: wide
    //   3542: invokeinterface 97 3 0
    //   3547: wide
    //   3551: getstatic 83	com/google/android/common/base/StringUtil:ESCAPE_STRINGS	Ljava/util/Map;
    //   3554: wide
    //   3558: sipush 937
    //   3561: invokestatic 89	java/lang/Character:valueOf	(C)Ljava/lang/Character;
    //   3564: wide
    //   3568: wide
    //   3572: ldc_w 337
    //   3575: wide
    //   3579: invokeinterface 97 3 0
    //   3584: wide
    //   3588: getstatic 83	com/google/android/common/base/StringUtil:ESCAPE_STRINGS	Ljava/util/Map;
    //   3591: wide
    //   3595: sipush 945
    //   3598: invokestatic 89	java/lang/Character:valueOf	(C)Ljava/lang/Character;
    //   3601: wide
    //   3605: wide
    //   3609: ldc_w 339
    //   3612: wide
    //   3616: invokeinterface 97 3 0
    //   3621: wide
    //   3625: getstatic 83	com/google/android/common/base/StringUtil:ESCAPE_STRINGS	Ljava/util/Map;
    //   3628: wide
    //   3632: sipush 946
    //   3635: invokestatic 89	java/lang/Character:valueOf	(C)Ljava/lang/Character;
    //   3638: wide
    //   3642: wide
    //   3646: ldc_w 341
    //   3649: wide
    //   3653: invokeinterface 97 3 0
    //   3658: wide
    //   3662: getstatic 83	com/google/android/common/base/StringUtil:ESCAPE_STRINGS	Ljava/util/Map;
    //   3665: wide
    //   3669: sipush 947
    //   3672: invokestatic 89	java/lang/Character:valueOf	(C)Ljava/lang/Character;
    //   3675: wide
    //   3679: wide
    //   3683: ldc_w 343
    //   3686: wide
    //   3690: invokeinterface 97 3 0
    //   3695: wide
    //   3699: getstatic 83	com/google/android/common/base/StringUtil:ESCAPE_STRINGS	Ljava/util/Map;
    //   3702: wide
    //   3706: sipush 948
    //   3709: invokestatic 89	java/lang/Character:valueOf	(C)Ljava/lang/Character;
    //   3712: wide
    //   3716: wide
    //   3720: ldc_w 345
    //   3723: wide
    //   3727: invokeinterface 97 3 0
    //   3732: wide
    //   3736: getstatic 83	com/google/android/common/base/StringUtil:ESCAPE_STRINGS	Ljava/util/Map;
    //   3739: wide
    //   3743: sipush 949
    //   3746: invokestatic 89	java/lang/Character:valueOf	(C)Ljava/lang/Character;
    //   3749: wide
    //   3753: wide
    //   3757: ldc_w 347
    //   3760: wide
    //   3764: invokeinterface 97 3 0
    //   3769: wide
    //   3773: getstatic 83	com/google/android/common/base/StringUtil:ESCAPE_STRINGS	Ljava/util/Map;
    //   3776: wide
    //   3780: sipush 950
    //   3783: invokestatic 89	java/lang/Character:valueOf	(C)Ljava/lang/Character;
    //   3786: wide
    //   3790: wide
    //   3794: ldc_w 349
    //   3797: wide
    //   3801: invokeinterface 97 3 0
    //   3806: wide
    //   3810: getstatic 83	com/google/android/common/base/StringUtil:ESCAPE_STRINGS	Ljava/util/Map;
    //   3813: wide
    //   3817: sipush 951
    //   3820: invokestatic 89	java/lang/Character:valueOf	(C)Ljava/lang/Character;
    //   3823: wide
    //   3827: wide
    //   3831: ldc_w 351
    //   3834: wide
    //   3838: invokeinterface 97 3 0
    //   3843: wide
    //   3847: getstatic 83	com/google/android/common/base/StringUtil:ESCAPE_STRINGS	Ljava/util/Map;
    //   3850: wide
    //   3854: sipush 952
    //   3857: invokestatic 89	java/lang/Character:valueOf	(C)Ljava/lang/Character;
    //   3860: wide
    //   3864: wide
    //   3868: ldc_w 353
    //   3871: wide
    //   3875: invokeinterface 97 3 0
    //   3880: wide
    //   3884: getstatic 83	com/google/android/common/base/StringUtil:ESCAPE_STRINGS	Ljava/util/Map;
    //   3887: wide
    //   3891: sipush 953
    //   3894: invokestatic 89	java/lang/Character:valueOf	(C)Ljava/lang/Character;
    //   3897: wide
    //   3901: wide
    //   3905: ldc_w 355
    //   3908: wide
    //   3912: invokeinterface 97 3 0
    //   3917: wide
    //   3921: getstatic 83	com/google/android/common/base/StringUtil:ESCAPE_STRINGS	Ljava/util/Map;
    //   3924: wide
    //   3928: sipush 954
    //   3931: invokestatic 89	java/lang/Character:valueOf	(C)Ljava/lang/Character;
    //   3934: wide
    //   3938: wide
    //   3942: ldc_w 357
    //   3945: wide
    //   3949: invokeinterface 97 3 0
    //   3954: wide
    //   3958: getstatic 83	com/google/android/common/base/StringUtil:ESCAPE_STRINGS	Ljava/util/Map;
    //   3961: wide
    //   3965: sipush 955
    //   3968: invokestatic 89	java/lang/Character:valueOf	(C)Ljava/lang/Character;
    //   3971: wide
    //   3975: wide
    //   3979: ldc_w 359
    //   3982: wide
    //   3986: invokeinterface 97 3 0
    //   3991: wide
    //   3995: getstatic 83	com/google/android/common/base/StringUtil:ESCAPE_STRINGS	Ljava/util/Map;
    //   3998: wide
    //   4002: sipush 956
    //   4005: invokestatic 89	java/lang/Character:valueOf	(C)Ljava/lang/Character;
    //   4008: wide
    //   4012: wide
    //   4016: ldc_w 361
    //   4019: wide
    //   4023: invokeinterface 97 3 0
    //   4028: wide
    //   4032: getstatic 83	com/google/android/common/base/StringUtil:ESCAPE_STRINGS	Ljava/util/Map;
    //   4035: wide
    //   4039: sipush 957
    //   4042: invokestatic 89	java/lang/Character:valueOf	(C)Ljava/lang/Character;
    //   4045: wide
    //   4049: wide
    //   4053: ldc_w 363
    //   4056: wide
    //   4060: invokeinterface 97 3 0
    //   4065: wide
    //   4069: getstatic 83	com/google/android/common/base/StringUtil:ESCAPE_STRINGS	Ljava/util/Map;
    //   4072: wide
    //   4076: sipush 958
    //   4079: invokestatic 89	java/lang/Character:valueOf	(C)Ljava/lang/Character;
    //   4082: wide
    //   4086: wide
    //   4090: ldc_w 365
    //   4093: wide
    //   4097: invokeinterface 97 3 0
    //   4102: wide
    //   4106: getstatic 83	com/google/android/common/base/StringUtil:ESCAPE_STRINGS	Ljava/util/Map;
    //   4109: wide
    //   4113: sipush 959
    //   4116: invokestatic 89	java/lang/Character:valueOf	(C)Ljava/lang/Character;
    //   4119: wide
    //   4123: wide
    //   4127: ldc_w 367
    //   4130: wide
    //   4134: invokeinterface 97 3 0
    //   4139: wide
    //   4143: getstatic 83	com/google/android/common/base/StringUtil:ESCAPE_STRINGS	Ljava/util/Map;
    //   4146: wide
    //   4150: sipush 960
    //   4153: invokestatic 89	java/lang/Character:valueOf	(C)Ljava/lang/Character;
    //   4156: wide
    //   4160: wide
    //   4164: ldc_w 369
    //   4167: wide
    //   4171: invokeinterface 97 3 0
    //   4176: wide
    //   4180: getstatic 83	com/google/android/common/base/StringUtil:ESCAPE_STRINGS	Ljava/util/Map;
    //   4183: wide
    //   4187: sipush 961
    //   4190: invokestatic 89	java/lang/Character:valueOf	(C)Ljava/lang/Character;
    //   4193: wide
    //   4197: wide
    //   4201: ldc_w 371
    //   4204: wide
    //   4208: invokeinterface 97 3 0
    //   4213: wide
    //   4217: getstatic 83	com/google/android/common/base/StringUtil:ESCAPE_STRINGS	Ljava/util/Map;
    //   4220: wide
    //   4224: sipush 962
    //   4227: invokestatic 89	java/lang/Character:valueOf	(C)Ljava/lang/Character;
    //   4230: wide
    //   4234: wide
    //   4238: ldc_w 373
    //   4241: wide
    //   4245: invokeinterface 97 3 0
    //   4250: wide
    //   4254: getstatic 83	com/google/android/common/base/StringUtil:ESCAPE_STRINGS	Ljava/util/Map;
    //   4257: wide
    //   4261: sipush 963
    //   4264: invokestatic 89	java/lang/Character:valueOf	(C)Ljava/lang/Character;
    //   4267: wide
    //   4271: wide
    //   4275: ldc_w 375
    //   4278: wide
    //   4282: invokeinterface 97 3 0
    //   4287: wide
    //   4291: getstatic 83	com/google/android/common/base/StringUtil:ESCAPE_STRINGS	Ljava/util/Map;
    //   4294: wide
    //   4298: sipush 964
    //   4301: invokestatic 89	java/lang/Character:valueOf	(C)Ljava/lang/Character;
    //   4304: wide
    //   4308: wide
    //   4312: ldc_w 377
    //   4315: wide
    //   4319: invokeinterface 97 3 0
    //   4324: wide
    //   4328: getstatic 83	com/google/android/common/base/StringUtil:ESCAPE_STRINGS	Ljava/util/Map;
    //   4331: wide
    //   4335: sipush 965
    //   4338: invokestatic 89	java/lang/Character:valueOf	(C)Ljava/lang/Character;
    //   4341: wide
    //   4345: wide
    //   4349: ldc_w 379
    //   4352: wide
    //   4356: invokeinterface 97 3 0
    //   4361: wide
    //   4365: getstatic 83	com/google/android/common/base/StringUtil:ESCAPE_STRINGS	Ljava/util/Map;
    //   4368: wide
    //   4372: sipush 966
    //   4375: invokestatic 89	java/lang/Character:valueOf	(C)Ljava/lang/Character;
    //   4378: wide
    //   4382: wide
    //   4386: ldc_w 381
    //   4389: wide
    //   4393: invokeinterface 97 3 0
    //   4398: wide
    //   4402: getstatic 83	com/google/android/common/base/StringUtil:ESCAPE_STRINGS	Ljava/util/Map;
    //   4405: wide
    //   4409: sipush 967
    //   4412: invokestatic 89	java/lang/Character:valueOf	(C)Ljava/lang/Character;
    //   4415: wide
    //   4419: wide
    //   4423: ldc_w 383
    //   4426: wide
    //   4430: invokeinterface 97 3 0
    //   4435: wide
    //   4439: getstatic 83	com/google/android/common/base/StringUtil:ESCAPE_STRINGS	Ljava/util/Map;
    //   4442: wide
    //   4446: sipush 968
    //   4449: invokestatic 89	java/lang/Character:valueOf	(C)Ljava/lang/Character;
    //   4452: wide
    //   4456: wide
    //   4460: ldc_w 385
    //   4463: wide
    //   4467: invokeinterface 97 3 0
    //   4472: wide
    //   4476: getstatic 83	com/google/android/common/base/StringUtil:ESCAPE_STRINGS	Ljava/util/Map;
    //   4479: wide
    //   4483: sipush 969
    //   4486: invokestatic 89	java/lang/Character:valueOf	(C)Ljava/lang/Character;
    //   4489: wide
    //   4493: wide
    //   4497: ldc_w 387
    //   4500: wide
    //   4504: invokeinterface 97 3 0
    //   4509: wide
    //   4513: getstatic 83	com/google/android/common/base/StringUtil:ESCAPE_STRINGS	Ljava/util/Map;
    //   4516: wide
    //   4520: sipush 977
    //   4523: invokestatic 89	java/lang/Character:valueOf	(C)Ljava/lang/Character;
    //   4526: wide
    //   4530: wide
    //   4534: ldc_w 389
    //   4537: wide
    //   4541: invokeinterface 97 3 0
    //   4546: wide
    //   4550: getstatic 83	com/google/android/common/base/StringUtil:ESCAPE_STRINGS	Ljava/util/Map;
    //   4553: wide
    //   4557: sipush 978
    //   4560: invokestatic 89	java/lang/Character:valueOf	(C)Ljava/lang/Character;
    //   4563: wide
    //   4567: wide
    //   4571: ldc_w 391
    //   4574: wide
    //   4578: invokeinterface 97 3 0
    //   4583: wide
    //   4587: getstatic 83	com/google/android/common/base/StringUtil:ESCAPE_STRINGS	Ljava/util/Map;
    //   4590: wide
    //   4594: sipush 982
    //   4597: invokestatic 89	java/lang/Character:valueOf	(C)Ljava/lang/Character;
    //   4600: wide
    //   4604: wide
    //   4608: ldc_w 393
    //   4611: wide
    //   4615: invokeinterface 97 3 0
    //   4620: wide
    //   4624: getstatic 83	com/google/android/common/base/StringUtil:ESCAPE_STRINGS	Ljava/util/Map;
    //   4627: wide
    //   4631: sipush 8226
    //   4634: invokestatic 89	java/lang/Character:valueOf	(C)Ljava/lang/Character;
    //   4637: wide
    //   4641: wide
    //   4645: ldc_w 395
    //   4648: wide
    //   4652: invokeinterface 97 3 0
    //   4657: wide
    //   4661: getstatic 83	com/google/android/common/base/StringUtil:ESCAPE_STRINGS	Ljava/util/Map;
    //   4664: wide
    //   4668: sipush 8230
    //   4671: invokestatic 89	java/lang/Character:valueOf	(C)Ljava/lang/Character;
    //   4674: wide
    //   4678: wide
    //   4682: ldc_w 397
    //   4685: wide
    //   4689: invokeinterface 97 3 0
    //   4694: wide
    //   4698: getstatic 83	com/google/android/common/base/StringUtil:ESCAPE_STRINGS	Ljava/util/Map;
    //   4701: wide
    //   4705: sipush 8242
    //   4708: invokestatic 89	java/lang/Character:valueOf	(C)Ljava/lang/Character;
    //   4711: wide
    //   4715: wide
    //   4719: ldc_w 399
    //   4722: wide
    //   4726: invokeinterface 97 3 0
    //   4731: wide
    //   4735: getstatic 83	com/google/android/common/base/StringUtil:ESCAPE_STRINGS	Ljava/util/Map;
    //   4738: wide
    //   4742: sipush 8243
    //   4745: invokestatic 89	java/lang/Character:valueOf	(C)Ljava/lang/Character;
    //   4748: wide
    //   4752: wide
    //   4756: ldc_w 401
    //   4759: wide
    //   4763: invokeinterface 97 3 0
    //   4768: wide
    //   4772: getstatic 83	com/google/android/common/base/StringUtil:ESCAPE_STRINGS	Ljava/util/Map;
    //   4775: wide
    //   4779: sipush 8254
    //   4782: invokestatic 89	java/lang/Character:valueOf	(C)Ljava/lang/Character;
    //   4785: wide
    //   4789: wide
    //   4793: ldc_w 403
    //   4796: wide
    //   4800: invokeinterface 97 3 0
    //   4805: wide
    //   4809: getstatic 83	com/google/android/common/base/StringUtil:ESCAPE_STRINGS	Ljava/util/Map;
    //   4812: wide
    //   4816: sipush 8260
    //   4819: invokestatic 89	java/lang/Character:valueOf	(C)Ljava/lang/Character;
    //   4822: wide
    //   4826: wide
    //   4830: ldc_w 405
    //   4833: wide
    //   4837: invokeinterface 97 3 0
    //   4842: wide
    //   4846: getstatic 83	com/google/android/common/base/StringUtil:ESCAPE_STRINGS	Ljava/util/Map;
    //   4849: wide
    //   4853: sipush 8472
    //   4856: invokestatic 89	java/lang/Character:valueOf	(C)Ljava/lang/Character;
    //   4859: wide
    //   4863: wide
    //   4867: ldc_w 407
    //   4870: wide
    //   4874: invokeinterface 97 3 0
    //   4879: wide
    //   4883: getstatic 83	com/google/android/common/base/StringUtil:ESCAPE_STRINGS	Ljava/util/Map;
    //   4886: wide
    //   4890: sipush 8465
    //   4893: invokestatic 89	java/lang/Character:valueOf	(C)Ljava/lang/Character;
    //   4896: wide
    //   4900: wide
    //   4904: ldc_w 409
    //   4907: wide
    //   4911: invokeinterface 97 3 0
    //   4916: wide
    //   4920: getstatic 83	com/google/android/common/base/StringUtil:ESCAPE_STRINGS	Ljava/util/Map;
    //   4923: wide
    //   4927: sipush 8476
    //   4930: invokestatic 89	java/lang/Character:valueOf	(C)Ljava/lang/Character;
    //   4933: wide
    //   4937: wide
    //   4941: ldc_w 411
    //   4944: wide
    //   4948: invokeinterface 97 3 0
    //   4953: wide
    //   4957: getstatic 83	com/google/android/common/base/StringUtil:ESCAPE_STRINGS	Ljava/util/Map;
    //   4960: wide
    //   4964: sipush 8482
    //   4967: invokestatic 89	java/lang/Character:valueOf	(C)Ljava/lang/Character;
    //   4970: wide
    //   4974: wide
    //   4978: ldc_w 413
    //   4981: wide
    //   4985: invokeinterface 97 3 0
    //   4990: wide
    //   4994: getstatic 83	com/google/android/common/base/StringUtil:ESCAPE_STRINGS	Ljava/util/Map;
    //   4997: wide
    //   5001: sipush 8501
    //   5004: invokestatic 89	java/lang/Character:valueOf	(C)Ljava/lang/Character;
    //   5007: wide
    //   5011: wide
    //   5015: ldc_w 415
    //   5018: wide
    //   5022: invokeinterface 97 3 0
    //   5027: wide
    //   5031: getstatic 83	com/google/android/common/base/StringUtil:ESCAPE_STRINGS	Ljava/util/Map;
    //   5034: wide
    //   5038: sipush 8592
    //   5041: invokestatic 89	java/lang/Character:valueOf	(C)Ljava/lang/Character;
    //   5044: wide
    //   5048: wide
    //   5052: ldc_w 417
    //   5055: wide
    //   5059: invokeinterface 97 3 0
    //   5064: wide
    //   5068: getstatic 83	com/google/android/common/base/StringUtil:ESCAPE_STRINGS	Ljava/util/Map;
    //   5071: wide
    //   5075: sipush 8593
    //   5078: invokestatic 89	java/lang/Character:valueOf	(C)Ljava/lang/Character;
    //   5081: wide
    //   5085: wide
    //   5089: ldc_w 419
    //   5092: wide
    //   5096: invokeinterface 97 3 0
    //   5101: wide
    //   5105: getstatic 83	com/google/android/common/base/StringUtil:ESCAPE_STRINGS	Ljava/util/Map;
    //   5108: wide
    //   5112: sipush 8594
    //   5115: invokestatic 89	java/lang/Character:valueOf	(C)Ljava/lang/Character;
    //   5118: wide
    //   5122: wide
    //   5126: ldc_w 421
    //   5129: wide
    //   5133: invokeinterface 97 3 0
    //   5138: wide
    //   5142: getstatic 83	com/google/android/common/base/StringUtil:ESCAPE_STRINGS	Ljava/util/Map;
    //   5145: wide
    //   5149: sipush 8595
    //   5152: invokestatic 89	java/lang/Character:valueOf	(C)Ljava/lang/Character;
    //   5155: wide
    //   5159: wide
    //   5163: ldc_w 423
    //   5166: wide
    //   5170: invokeinterface 97 3 0
    //   5175: wide
    //   5179: getstatic 83	com/google/android/common/base/StringUtil:ESCAPE_STRINGS	Ljava/util/Map;
    //   5182: wide
    //   5186: sipush 8596
    //   5189: invokestatic 89	java/lang/Character:valueOf	(C)Ljava/lang/Character;
    //   5192: wide
    //   5196: wide
    //   5200: ldc_w 425
    //   5203: wide
    //   5207: invokeinterface 97 3 0
    //   5212: wide
    //   5216: getstatic 83	com/google/android/common/base/StringUtil:ESCAPE_STRINGS	Ljava/util/Map;
    //   5219: wide
    //   5223: sipush 8629
    //   5226: invokestatic 89	java/lang/Character:valueOf	(C)Ljava/lang/Character;
    //   5229: wide
    //   5233: wide
    //   5237: ldc_w 427
    //   5240: wide
    //   5244: invokeinterface 97 3 0
    //   5249: wide
    //   5253: getstatic 83	com/google/android/common/base/StringUtil:ESCAPE_STRINGS	Ljava/util/Map;
    //   5256: wide
    //   5260: sipush 8656
    //   5263: invokestatic 89	java/lang/Character:valueOf	(C)Ljava/lang/Character;
    //   5266: wide
    //   5270: wide
    //   5274: ldc_w 429
    //   5277: wide
    //   5281: invokeinterface 97 3 0
    //   5286: wide
    //   5290: getstatic 83	com/google/android/common/base/StringUtil:ESCAPE_STRINGS	Ljava/util/Map;
    //   5293: wide
    //   5297: sipush 8657
    //   5300: invokestatic 89	java/lang/Character:valueOf	(C)Ljava/lang/Character;
    //   5303: wide
    //   5307: wide
    //   5311: ldc_w 431
    //   5314: wide
    //   5318: invokeinterface 97 3 0
    //   5323: wide
    //   5327: getstatic 83	com/google/android/common/base/StringUtil:ESCAPE_STRINGS	Ljava/util/Map;
    //   5330: wide
    //   5334: sipush 8658
    //   5337: invokestatic 89	java/lang/Character:valueOf	(C)Ljava/lang/Character;
    //   5340: wide
    //   5344: wide
    //   5348: ldc_w 433
    //   5351: wide
    //   5355: invokeinterface 97 3 0
    //   5360: wide
    //   5364: getstatic 83	com/google/android/common/base/StringUtil:ESCAPE_STRINGS	Ljava/util/Map;
    //   5367: wide
    //   5371: sipush 8659
    //   5374: invokestatic 89	java/lang/Character:valueOf	(C)Ljava/lang/Character;
    //   5377: wide
    //   5381: wide
    //   5385: ldc_w 435
    //   5388: wide
    //   5392: invokeinterface 97 3 0
    //   5397: wide
    //   5401: getstatic 83	com/google/android/common/base/StringUtil:ESCAPE_STRINGS	Ljava/util/Map;
    //   5404: wide
    //   5408: sipush 8660
    //   5411: invokestatic 89	java/lang/Character:valueOf	(C)Ljava/lang/Character;
    //   5414: wide
    //   5418: wide
    //   5422: ldc_w 437
    //   5425: wide
    //   5429: invokeinterface 97 3 0
    //   5434: wide
    //   5438: getstatic 83	com/google/android/common/base/StringUtil:ESCAPE_STRINGS	Ljava/util/Map;
    //   5441: wide
    //   5445: sipush 8704
    //   5448: invokestatic 89	java/lang/Character:valueOf	(C)Ljava/lang/Character;
    //   5451: wide
    //   5455: wide
    //   5459: ldc_w 439
    //   5462: wide
    //   5466: invokeinterface 97 3 0
    //   5471: wide
    //   5475: getstatic 83	com/google/android/common/base/StringUtil:ESCAPE_STRINGS	Ljava/util/Map;
    //   5478: wide
    //   5482: sipush 8706
    //   5485: invokestatic 89	java/lang/Character:valueOf	(C)Ljava/lang/Character;
    //   5488: wide
    //   5492: wide
    //   5496: ldc_w 441
    //   5499: wide
    //   5503: invokeinterface 97 3 0
    //   5508: wide
    //   5512: getstatic 83	com/google/android/common/base/StringUtil:ESCAPE_STRINGS	Ljava/util/Map;
    //   5515: wide
    //   5519: sipush 8707
    //   5522: invokestatic 89	java/lang/Character:valueOf	(C)Ljava/lang/Character;
    //   5525: wide
    //   5529: wide
    //   5533: ldc_w 443
    //   5536: wide
    //   5540: invokeinterface 97 3 0
    //   5545: wide
    //   5549: getstatic 83	com/google/android/common/base/StringUtil:ESCAPE_STRINGS	Ljava/util/Map;
    //   5552: wide
    //   5556: sipush 8709
    //   5559: invokestatic 89	java/lang/Character:valueOf	(C)Ljava/lang/Character;
    //   5562: wide
    //   5566: wide
    //   5570: ldc_w 445
    //   5573: wide
    //   5577: invokeinterface 97 3 0
    //   5582: wide
    //   5586: getstatic 83	com/google/android/common/base/StringUtil:ESCAPE_STRINGS	Ljava/util/Map;
    //   5589: wide
    //   5593: sipush 8711
    //   5596: invokestatic 89	java/lang/Character:valueOf	(C)Ljava/lang/Character;
    //   5599: wide
    //   5603: wide
    //   5607: ldc_w 447
    //   5610: wide
    //   5614: invokeinterface 97 3 0
    //   5619: wide
    //   5623: getstatic 83	com/google/android/common/base/StringUtil:ESCAPE_STRINGS	Ljava/util/Map;
    //   5626: wide
    //   5630: sipush 8712
    //   5633: invokestatic 89	java/lang/Character:valueOf	(C)Ljava/lang/Character;
    //   5636: wide
    //   5640: wide
    //   5644: ldc_w 449
    //   5647: wide
    //   5651: invokeinterface 97 3 0
    //   5656: wide
    //   5660: getstatic 83	com/google/android/common/base/StringUtil:ESCAPE_STRINGS	Ljava/util/Map;
    //   5663: wide
    //   5667: sipush 8713
    //   5670: invokestatic 89	java/lang/Character:valueOf	(C)Ljava/lang/Character;
    //   5673: wide
    //   5677: wide
    //   5681: ldc_w 451
    //   5684: wide
    //   5688: invokeinterface 97 3 0
    //   5693: wide
    //   5697: getstatic 83	com/google/android/common/base/StringUtil:ESCAPE_STRINGS	Ljava/util/Map;
    //   5700: wide
    //   5704: sipush 8715
    //   5707: invokestatic 89	java/lang/Character:valueOf	(C)Ljava/lang/Character;
    //   5710: wide
    //   5714: wide
    //   5718: ldc_w 453
    //   5721: wide
    //   5725: invokeinterface 97 3 0
    //   5730: wide
    //   5734: getstatic 83	com/google/android/common/base/StringUtil:ESCAPE_STRINGS	Ljava/util/Map;
    //   5737: wide
    //   5741: sipush 8719
    //   5744: invokestatic 89	java/lang/Character:valueOf	(C)Ljava/lang/Character;
    //   5747: wide
    //   5751: wide
    //   5755: ldc_w 455
    //   5758: wide
    //   5762: invokeinterface 97 3 0
    //   5767: wide
    //   5771: getstatic 83	com/google/android/common/base/StringUtil:ESCAPE_STRINGS	Ljava/util/Map;
    //   5774: wide
    //   5778: sipush 8721
    //   5781: invokestatic 89	java/lang/Character:valueOf	(C)Ljava/lang/Character;
    //   5784: wide
    //   5788: wide
    //   5792: ldc_w 457
    //   5795: wide
    //   5799: invokeinterface 97 3 0
    //   5804: wide
    //   5808: getstatic 83	com/google/android/common/base/StringUtil:ESCAPE_STRINGS	Ljava/util/Map;
    //   5811: wide
    //   5815: sipush 8722
    //   5818: invokestatic 89	java/lang/Character:valueOf	(C)Ljava/lang/Character;
    //   5821: wide
    //   5825: wide
    //   5829: ldc_w 459
    //   5832: wide
    //   5836: invokeinterface 97 3 0
    //   5841: wide
    //   5845: getstatic 83	com/google/android/common/base/StringUtil:ESCAPE_STRINGS	Ljava/util/Map;
    //   5848: wide
    //   5852: sipush 8727
    //   5855: invokestatic 89	java/lang/Character:valueOf	(C)Ljava/lang/Character;
    //   5858: wide
    //   5862: wide
    //   5866: ldc_w 461
    //   5869: wide
    //   5873: invokeinterface 97 3 0
    //   5878: wide
    //   5882: getstatic 83	com/google/android/common/base/StringUtil:ESCAPE_STRINGS	Ljava/util/Map;
    //   5885: wide
    //   5889: sipush 8730
    //   5892: invokestatic 89	java/lang/Character:valueOf	(C)Ljava/lang/Character;
    //   5895: wide
    //   5899: wide
    //   5903: ldc_w 463
    //   5906: wide
    //   5910: invokeinterface 97 3 0
    //   5915: wide
    //   5919: getstatic 83	com/google/android/common/base/StringUtil:ESCAPE_STRINGS	Ljava/util/Map;
    //   5922: wide
    //   5926: sipush 8733
    //   5929: invokestatic 89	java/lang/Character:valueOf	(C)Ljava/lang/Character;
    //   5932: wide
    //   5936: wide
    //   5940: ldc_w 465
    //   5943: wide
    //   5947: invokeinterface 97 3 0
    //   5952: wide
    //   5956: getstatic 83	com/google/android/common/base/StringUtil:ESCAPE_STRINGS	Ljava/util/Map;
    //   5959: wide
    //   5963: sipush 8734
    //   5966: invokestatic 89	java/lang/Character:valueOf	(C)Ljava/lang/Character;
    //   5969: wide
    //   5973: wide
    //   5977: ldc_w 467
    //   5980: wide
    //   5984: invokeinterface 97 3 0
    //   5989: wide
    //   5993: getstatic 83	com/google/android/common/base/StringUtil:ESCAPE_STRINGS	Ljava/util/Map;
    //   5996: wide
    //   6000: sipush 8736
    //   6003: invokestatic 89	java/lang/Character:valueOf	(C)Ljava/lang/Character;
    //   6006: wide
    //   6010: wide
    //   6014: ldc_w 469
    //   6017: wide
    //   6021: invokeinterface 97 3 0
    //   6026: wide
    //   6030: getstatic 83	com/google/android/common/base/StringUtil:ESCAPE_STRINGS	Ljava/util/Map;
    //   6033: wide
    //   6037: sipush 8743
    //   6040: invokestatic 89	java/lang/Character:valueOf	(C)Ljava/lang/Character;
    //   6043: wide
    //   6047: wide
    //   6051: ldc_w 471
    //   6054: wide
    //   6058: invokeinterface 97 3 0
    //   6063: wide
    //   6067: getstatic 83	com/google/android/common/base/StringUtil:ESCAPE_STRINGS	Ljava/util/Map;
    //   6070: wide
    //   6074: sipush 8744
    //   6077: invokestatic 89	java/lang/Character:valueOf	(C)Ljava/lang/Character;
    //   6080: wide
    //   6084: wide
    //   6088: ldc_w 473
    //   6091: wide
    //   6095: invokeinterface 97 3 0
    //   6100: wide
    //   6104: getstatic 83	com/google/android/common/base/StringUtil:ESCAPE_STRINGS	Ljava/util/Map;
    //   6107: wide
    //   6111: sipush 8745
    //   6114: invokestatic 89	java/lang/Character:valueOf	(C)Ljava/lang/Character;
    //   6117: wide
    //   6121: wide
    //   6125: ldc_w 475
    //   6128: wide
    //   6132: invokeinterface 97 3 0
    //   6137: wide
    //   6141: getstatic 83	com/google/android/common/base/StringUtil:ESCAPE_STRINGS	Ljava/util/Map;
    //   6144: wide
    //   6148: sipush 8746
    //   6151: invokestatic 89	java/lang/Character:valueOf	(C)Ljava/lang/Character;
    //   6154: wide
    //   6158: wide
    //   6162: ldc_w 477
    //   6165: wide
    //   6169: invokeinterface 97 3 0
    //   6174: wide
    //   6178: getstatic 83	com/google/android/common/base/StringUtil:ESCAPE_STRINGS	Ljava/util/Map;
    //   6181: wide
    //   6185: sipush 8747
    //   6188: invokestatic 89	java/lang/Character:valueOf	(C)Ljava/lang/Character;
    //   6191: wide
    //   6195: wide
    //   6199: ldc_w 479
    //   6202: wide
    //   6206: invokeinterface 97 3 0
    //   6211: wide
    //   6215: getstatic 83	com/google/android/common/base/StringUtil:ESCAPE_STRINGS	Ljava/util/Map;
    //   6218: wide
    //   6222: sipush 8756
    //   6225: invokestatic 89	java/lang/Character:valueOf	(C)Ljava/lang/Character;
    //   6228: wide
    //   6232: wide
    //   6236: ldc_w 481
    //   6239: wide
    //   6243: invokeinterface 97 3 0
    //   6248: wide
    //   6252: getstatic 83	com/google/android/common/base/StringUtil:ESCAPE_STRINGS	Ljava/util/Map;
    //   6255: wide
    //   6259: sipush 8764
    //   6262: invokestatic 89	java/lang/Character:valueOf	(C)Ljava/lang/Character;
    //   6265: wide
    //   6269: wide
    //   6273: ldc_w 483
    //   6276: wide
    //   6280: invokeinterface 97 3 0
    //   6285: wide
    //   6289: getstatic 83	com/google/android/common/base/StringUtil:ESCAPE_STRINGS	Ljava/util/Map;
    //   6292: wide
    //   6296: sipush 8773
    //   6299: invokestatic 89	java/lang/Character:valueOf	(C)Ljava/lang/Character;
    //   6302: wide
    //   6306: wide
    //   6310: ldc_w 485
    //   6313: wide
    //   6317: invokeinterface 97 3 0
    //   6322: wide
    //   6326: getstatic 83	com/google/android/common/base/StringUtil:ESCAPE_STRINGS	Ljava/util/Map;
    //   6329: wide
    //   6333: sipush 8776
    //   6336: invokestatic 89	java/lang/Character:valueOf	(C)Ljava/lang/Character;
    //   6339: wide
    //   6343: wide
    //   6347: ldc_w 487
    //   6350: wide
    //   6354: invokeinterface 97 3 0
    //   6359: wide
    //   6363: getstatic 83	com/google/android/common/base/StringUtil:ESCAPE_STRINGS	Ljava/util/Map;
    //   6366: wide
    //   6370: sipush 8800
    //   6373: invokestatic 89	java/lang/Character:valueOf	(C)Ljava/lang/Character;
    //   6376: wide
    //   6380: wide
    //   6384: ldc_w 489
    //   6387: wide
    //   6391: invokeinterface 97 3 0
    //   6396: wide
    //   6400: getstatic 83	com/google/android/common/base/StringUtil:ESCAPE_STRINGS	Ljava/util/Map;
    //   6403: wide
    //   6407: sipush 8801
    //   6410: invokestatic 89	java/lang/Character:valueOf	(C)Ljava/lang/Character;
    //   6413: wide
    //   6417: wide
    //   6421: ldc_w 491
    //   6424: wide
    //   6428: invokeinterface 97 3 0
    //   6433: wide
    //   6437: getstatic 83	com/google/android/common/base/StringUtil:ESCAPE_STRINGS	Ljava/util/Map;
    //   6440: wide
    //   6444: sipush 8804
    //   6447: invokestatic 89	java/lang/Character:valueOf	(C)Ljava/lang/Character;
    //   6450: wide
    //   6454: wide
    //   6458: ldc_w 493
    //   6461: wide
    //   6465: invokeinterface 97 3 0
    //   6470: wide
    //   6474: getstatic 83	com/google/android/common/base/StringUtil:ESCAPE_STRINGS	Ljava/util/Map;
    //   6477: wide
    //   6481: sipush 8805
    //   6484: invokestatic 89	java/lang/Character:valueOf	(C)Ljava/lang/Character;
    //   6487: wide
    //   6491: wide
    //   6495: ldc_w 495
    //   6498: wide
    //   6502: invokeinterface 97 3 0
    //   6507: wide
    //   6511: getstatic 83	com/google/android/common/base/StringUtil:ESCAPE_STRINGS	Ljava/util/Map;
    //   6514: wide
    //   6518: sipush 8834
    //   6521: invokestatic 89	java/lang/Character:valueOf	(C)Ljava/lang/Character;
    //   6524: wide
    //   6528: wide
    //   6532: ldc_w 497
    //   6535: wide
    //   6539: invokeinterface 97 3 0
    //   6544: wide
    //   6548: getstatic 83	com/google/android/common/base/StringUtil:ESCAPE_STRINGS	Ljava/util/Map;
    //   6551: wide
    //   6555: sipush 8835
    //   6558: invokestatic 89	java/lang/Character:valueOf	(C)Ljava/lang/Character;
    //   6561: wide
    //   6565: wide
    //   6569: ldc_w 499
    //   6572: wide
    //   6576: invokeinterface 97 3 0
    //   6581: wide
    //   6585: getstatic 83	com/google/android/common/base/StringUtil:ESCAPE_STRINGS	Ljava/util/Map;
    //   6588: wide
    //   6592: sipush 8836
    //   6595: invokestatic 89	java/lang/Character:valueOf	(C)Ljava/lang/Character;
    //   6598: wide
    //   6602: wide
    //   6606: ldc_w 501
    //   6609: wide
    //   6613: invokeinterface 97 3 0
    //   6618: wide
    //   6622: getstatic 83	com/google/android/common/base/StringUtil:ESCAPE_STRINGS	Ljava/util/Map;
    //   6625: wide
    //   6629: sipush 8838
    //   6632: invokestatic 89	java/lang/Character:valueOf	(C)Ljava/lang/Character;
    //   6635: wide
    //   6639: wide
    //   6643: ldc_w 503
    //   6646: wide
    //   6650: invokeinterface 97 3 0
    //   6655: wide
    //   6659: getstatic 83	com/google/android/common/base/StringUtil:ESCAPE_STRINGS	Ljava/util/Map;
    //   6662: wide
    //   6666: sipush 8839
    //   6669: invokestatic 89	java/lang/Character:valueOf	(C)Ljava/lang/Character;
    //   6672: wide
    //   6676: wide
    //   6680: ldc_w 505
    //   6683: wide
    //   6687: invokeinterface 97 3 0
    //   6692: wide
    //   6696: getstatic 83	com/google/android/common/base/StringUtil:ESCAPE_STRINGS	Ljava/util/Map;
    //   6699: wide
    //   6703: sipush 8853
    //   6706: invokestatic 89	java/lang/Character:valueOf	(C)Ljava/lang/Character;
    //   6709: wide
    //   6713: wide
    //   6717: ldc_w 507
    //   6720: wide
    //   6724: invokeinterface 97 3 0
    //   6729: wide
    //   6733: getstatic 83	com/google/android/common/base/StringUtil:ESCAPE_STRINGS	Ljava/util/Map;
    //   6736: wide
    //   6740: sipush 8855
    //   6743: invokestatic 89	java/lang/Character:valueOf	(C)Ljava/lang/Character;
    //   6746: wide
    //   6750: wide
    //   6754: ldc_w 509
    //   6757: wide
    //   6761: invokeinterface 97 3 0
    //   6766: wide
    //   6770: getstatic 83	com/google/android/common/base/StringUtil:ESCAPE_STRINGS	Ljava/util/Map;
    //   6773: wide
    //   6777: sipush 8869
    //   6780: invokestatic 89	java/lang/Character:valueOf	(C)Ljava/lang/Character;
    //   6783: wide
    //   6787: wide
    //   6791: ldc_w 511
    //   6794: wide
    //   6798: invokeinterface 97 3 0
    //   6803: wide
    //   6807: getstatic 83	com/google/android/common/base/StringUtil:ESCAPE_STRINGS	Ljava/util/Map;
    //   6810: wide
    //   6814: sipush 8901
    //   6817: invokestatic 89	java/lang/Character:valueOf	(C)Ljava/lang/Character;
    //   6820: wide
    //   6824: wide
    //   6828: ldc_w 513
    //   6831: wide
    //   6835: invokeinterface 97 3 0
    //   6840: wide
    //   6844: getstatic 83	com/google/android/common/base/StringUtil:ESCAPE_STRINGS	Ljava/util/Map;
    //   6847: wide
    //   6851: sipush 8968
    //   6854: invokestatic 89	java/lang/Character:valueOf	(C)Ljava/lang/Character;
    //   6857: wide
    //   6861: wide
    //   6865: ldc_w 515
    //   6868: wide
    //   6872: invokeinterface 97 3 0
    //   6877: wide
    //   6881: getstatic 83	com/google/android/common/base/StringUtil:ESCAPE_STRINGS	Ljava/util/Map;
    //   6884: wide
    //   6888: sipush 8969
    //   6891: invokestatic 89	java/lang/Character:valueOf	(C)Ljava/lang/Character;
    //   6894: wide
    //   6898: wide
    //   6902: ldc_w 517
    //   6905: wide
    //   6909: invokeinterface 97 3 0
    //   6914: wide
    //   6918: getstatic 83	com/google/android/common/base/StringUtil:ESCAPE_STRINGS	Ljava/util/Map;
    //   6921: wide
    //   6925: sipush 8970
    //   6928: invokestatic 89	java/lang/Character:valueOf	(C)Ljava/lang/Character;
    //   6931: wide
    //   6935: wide
    //   6939: ldc_w 519
    //   6942: wide
    //   6946: invokeinterface 97 3 0
    //   6951: wide
    //   6955: getstatic 83	com/google/android/common/base/StringUtil:ESCAPE_STRINGS	Ljava/util/Map;
    //   6958: wide
    //   6962: sipush 8971
    //   6965: invokestatic 89	java/lang/Character:valueOf	(C)Ljava/lang/Character;
    //   6968: wide
    //   6972: wide
    //   6976: ldc_w 521
    //   6979: wide
    //   6983: invokeinterface 97 3 0
    //   6988: wide
    //   6992: getstatic 83	com/google/android/common/base/StringUtil:ESCAPE_STRINGS	Ljava/util/Map;
    //   6995: wide
    //   6999: sipush 9001
    //   7002: invokestatic 89	java/lang/Character:valueOf	(C)Ljava/lang/Character;
    //   7005: wide
    //   7009: wide
    //   7013: ldc_w 523
    //   7016: wide
    //   7020: invokeinterface 97 3 0
    //   7025: wide
    //   7029: getstatic 83	com/google/android/common/base/StringUtil:ESCAPE_STRINGS	Ljava/util/Map;
    //   7032: wide
    //   7036: sipush 9002
    //   7039: invokestatic 89	java/lang/Character:valueOf	(C)Ljava/lang/Character;
    //   7042: wide
    //   7046: wide
    //   7050: ldc_w 525
    //   7053: wide
    //   7057: invokeinterface 97 3 0
    //   7062: wide
    //   7066: getstatic 83	com/google/android/common/base/StringUtil:ESCAPE_STRINGS	Ljava/util/Map;
    //   7069: wide
    //   7073: sipush 9674
    //   7076: invokestatic 89	java/lang/Character:valueOf	(C)Ljava/lang/Character;
    //   7079: wide
    //   7083: wide
    //   7087: ldc_w 527
    //   7090: wide
    //   7094: invokeinterface 97 3 0
    //   7099: wide
    //   7103: getstatic 83	com/google/android/common/base/StringUtil:ESCAPE_STRINGS	Ljava/util/Map;
    //   7106: wide
    //   7110: sipush 9824
    //   7113: invokestatic 89	java/lang/Character:valueOf	(C)Ljava/lang/Character;
    //   7116: wide
    //   7120: wide
    //   7124: ldc_w 529
    //   7127: wide
    //   7131: invokeinterface 97 3 0
    //   7136: wide
    //   7140: getstatic 83	com/google/android/common/base/StringUtil:ESCAPE_STRINGS	Ljava/util/Map;
    //   7143: wide
    //   7147: sipush 9827
    //   7150: invokestatic 89	java/lang/Character:valueOf	(C)Ljava/lang/Character;
    //   7153: wide
    //   7157: wide
    //   7161: ldc_w 531
    //   7164: wide
    //   7168: invokeinterface 97 3 0
    //   7173: wide
    //   7177: getstatic 83	com/google/android/common/base/StringUtil:ESCAPE_STRINGS	Ljava/util/Map;
    //   7180: wide
    //   7184: sipush 9829
    //   7187: invokestatic 89	java/lang/Character:valueOf	(C)Ljava/lang/Character;
    //   7190: wide
    //   7194: wide
    //   7198: ldc_w 533
    //   7201: wide
    //   7205: invokeinterface 97 3 0
    //   7210: wide
    //   7214: getstatic 83	com/google/android/common/base/StringUtil:ESCAPE_STRINGS	Ljava/util/Map;
    //   7217: wide
    //   7221: sipush 9830
    //   7224: invokestatic 89	java/lang/Character:valueOf	(C)Ljava/lang/Character;
    //   7227: wide
    //   7231: wide
    //   7235: ldc_w 535
    //   7238: wide
    //   7242: invokeinterface 97 3 0
    //   7247: wide
    //   7251: getstatic 83	com/google/android/common/base/StringUtil:ESCAPE_STRINGS	Ljava/util/Map;
    //   7254: wide
    //   7258: bipush 34
    //   7260: invokestatic 89	java/lang/Character:valueOf	(C)Ljava/lang/Character;
    //   7263: wide
    //   7267: wide
    //   7271: ldc_w 537
    //   7274: wide
    //   7278: invokeinterface 97 3 0
    //   7283: wide
    //   7287: getstatic 83	com/google/android/common/base/StringUtil:ESCAPE_STRINGS	Ljava/util/Map;
    //   7290: wide
    //   7294: bipush 38
    //   7296: invokestatic 89	java/lang/Character:valueOf	(C)Ljava/lang/Character;
    //   7299: wide
    //   7303: wide
    //   7307: ldc_w 539
    //   7310: wide
    //   7314: invokeinterface 97 3 0
    //   7319: wide
    //   7323: getstatic 83	com/google/android/common/base/StringUtil:ESCAPE_STRINGS	Ljava/util/Map;
    //   7326: wide
    //   7330: bipush 60
    //   7332: invokestatic 89	java/lang/Character:valueOf	(C)Ljava/lang/Character;
    //   7335: wide
    //   7339: wide
    //   7343: ldc_w 541
    //   7346: wide
    //   7350: invokeinterface 97 3 0
    //   7355: wide
    //   7359: getstatic 83	com/google/android/common/base/StringUtil:ESCAPE_STRINGS	Ljava/util/Map;
    //   7362: wide
    //   7366: bipush 62
    //   7368: invokestatic 89	java/lang/Character:valueOf	(C)Ljava/lang/Character;
    //   7371: wide
    //   7375: wide
    //   7379: ldc_w 543
    //   7382: wide
    //   7386: invokeinterface 97 3 0
    //   7391: wide
    //   7395: getstatic 83	com/google/android/common/base/StringUtil:ESCAPE_STRINGS	Ljava/util/Map;
    //   7398: wide
    //   7402: sipush 338
    //   7405: invokestatic 89	java/lang/Character:valueOf	(C)Ljava/lang/Character;
    //   7408: wide
    //   7412: wide
    //   7416: ldc_w 545
    //   7419: wide
    //   7423: invokeinterface 97 3 0
    //   7428: wide
    //   7432: getstatic 83	com/google/android/common/base/StringUtil:ESCAPE_STRINGS	Ljava/util/Map;
    //   7435: wide
    //   7439: sipush 339
    //   7442: invokestatic 89	java/lang/Character:valueOf	(C)Ljava/lang/Character;
    //   7445: wide
    //   7449: wide
    //   7453: ldc_w 547
    //   7456: wide
    //   7460: invokeinterface 97 3 0
    //   7465: wide
    //   7469: getstatic 83	com/google/android/common/base/StringUtil:ESCAPE_STRINGS	Ljava/util/Map;
    //   7472: wide
    //   7476: sipush 352
    //   7479: invokestatic 89	java/lang/Character:valueOf	(C)Ljava/lang/Character;
    //   7482: wide
    //   7486: wide
    //   7490: ldc_w 549
    //   7493: wide
    //   7497: invokeinterface 97 3 0
    //   7502: wide
    //   7506: getstatic 83	com/google/android/common/base/StringUtil:ESCAPE_STRINGS	Ljava/util/Map;
    //   7509: wide
    //   7513: sipush 353
    //   7516: invokestatic 89	java/lang/Character:valueOf	(C)Ljava/lang/Character;
    //   7519: wide
    //   7523: wide
    //   7527: ldc_w 551
    //   7530: wide
    //   7534: invokeinterface 97 3 0
    //   7539: wide
    //   7543: getstatic 83	com/google/android/common/base/StringUtil:ESCAPE_STRINGS	Ljava/util/Map;
    //   7546: wide
    //   7550: sipush 376
    //   7553: invokestatic 89	java/lang/Character:valueOf	(C)Ljava/lang/Character;
    //   7556: wide
    //   7560: wide
    //   7564: ldc_w 553
    //   7567: wide
    //   7571: invokeinterface 97 3 0
    //   7576: wide
    //   7580: getstatic 83	com/google/android/common/base/StringUtil:ESCAPE_STRINGS	Ljava/util/Map;
    //   7583: wide
    //   7587: sipush 710
    //   7590: invokestatic 89	java/lang/Character:valueOf	(C)Ljava/lang/Character;
    //   7593: wide
    //   7597: wide
    //   7601: ldc_w 555
    //   7604: wide
    //   7608: invokeinterface 97 3 0
    //   7613: wide
    //   7617: getstatic 83	com/google/android/common/base/StringUtil:ESCAPE_STRINGS	Ljava/util/Map;
    //   7620: wide
    //   7624: sipush 732
    //   7627: invokestatic 89	java/lang/Character:valueOf	(C)Ljava/lang/Character;
    //   7630: wide
    //   7634: wide
    //   7638: ldc_w 557
    //   7641: wide
    //   7645: invokeinterface 97 3 0
    //   7650: wide
    //   7654: getstatic 83	com/google/android/common/base/StringUtil:ESCAPE_STRINGS	Ljava/util/Map;
    //   7657: wide
    //   7661: sipush 8194
    //   7664: invokestatic 89	java/lang/Character:valueOf	(C)Ljava/lang/Character;
    //   7667: wide
    //   7671: wide
    //   7675: ldc_w 559
    //   7678: wide
    //   7682: invokeinterface 97 3 0
    //   7687: wide
    //   7691: getstatic 83	com/google/android/common/base/StringUtil:ESCAPE_STRINGS	Ljava/util/Map;
    //   7694: wide
    //   7698: sipush 8195
    //   7701: invokestatic 89	java/lang/Character:valueOf	(C)Ljava/lang/Character;
    //   7704: wide
    //   7708: wide
    //   7712: ldc_w 561
    //   7715: wide
    //   7719: invokeinterface 97 3 0
    //   7724: wide
    //   7728: getstatic 83	com/google/android/common/base/StringUtil:ESCAPE_STRINGS	Ljava/util/Map;
    //   7731: wide
    //   7735: sipush 8201
    //   7738: invokestatic 89	java/lang/Character:valueOf	(C)Ljava/lang/Character;
    //   7741: wide
    //   7745: wide
    //   7749: ldc_w 563
    //   7752: wide
    //   7756: invokeinterface 97 3 0
    //   7761: wide
    //   7765: getstatic 83	com/google/android/common/base/StringUtil:ESCAPE_STRINGS	Ljava/util/Map;
    //   7768: wide
    //   7772: sipush 8204
    //   7775: invokestatic 89	java/lang/Character:valueOf	(C)Ljava/lang/Character;
    //   7778: wide
    //   7782: wide
    //   7786: ldc_w 565
    //   7789: wide
    //   7793: invokeinterface 97 3 0
    //   7798: wide
    //   7802: getstatic 83	com/google/android/common/base/StringUtil:ESCAPE_STRINGS	Ljava/util/Map;
    //   7805: wide
    //   7809: sipush 8205
    //   7812: invokestatic 89	java/lang/Character:valueOf	(C)Ljava/lang/Character;
    //   7815: wide
    //   7819: wide
    //   7823: ldc_w 567
    //   7826: wide
    //   7830: invokeinterface 97 3 0
    //   7835: wide
    //   7839: getstatic 83	com/google/android/common/base/StringUtil:ESCAPE_STRINGS	Ljava/util/Map;
    //   7842: wide
    //   7846: sipush 8206
    //   7849: invokestatic 89	java/lang/Character:valueOf	(C)Ljava/lang/Character;
    //   7852: wide
    //   7856: wide
    //   7860: ldc_w 569
    //   7863: wide
    //   7867: invokeinterface 97 3 0
    //   7872: wide
    //   7876: getstatic 83	com/google/android/common/base/StringUtil:ESCAPE_STRINGS	Ljava/util/Map;
    //   7879: wide
    //   7883: sipush 8207
    //   7886: invokestatic 89	java/lang/Character:valueOf	(C)Ljava/lang/Character;
    //   7889: wide
    //   7893: wide
    //   7897: ldc_w 571
    //   7900: wide
    //   7904: invokeinterface 97 3 0
    //   7909: wide
    //   7913: getstatic 83	com/google/android/common/base/StringUtil:ESCAPE_STRINGS	Ljava/util/Map;
    //   7916: wide
    //   7920: sipush 8211
    //   7923: invokestatic 89	java/lang/Character:valueOf	(C)Ljava/lang/Character;
    //   7926: wide
    //   7930: wide
    //   7934: ldc_w 573
    //   7937: wide
    //   7941: invokeinterface 97 3 0
    //   7946: wide
    //   7950: getstatic 83	com/google/android/common/base/StringUtil:ESCAPE_STRINGS	Ljava/util/Map;
    //   7953: wide
    //   7957: sipush 8212
    //   7960: invokestatic 89	java/lang/Character:valueOf	(C)Ljava/lang/Character;
    //   7963: wide
    //   7967: wide
    //   7971: ldc_w 575
    //   7974: wide
    //   7978: invokeinterface 97 3 0
    //   7983: wide
    //   7987: getstatic 83	com/google/android/common/base/StringUtil:ESCAPE_STRINGS	Ljava/util/Map;
    //   7990: wide
    //   7994: sipush 8216
    //   7997: invokestatic 89	java/lang/Character:valueOf	(C)Ljava/lang/Character;
    //   8000: wide
    //   8004: wide
    //   8008: ldc_w 577
    //   8011: wide
    //   8015: invokeinterface 97 3 0
    //   8020: wide
    //   8024: getstatic 83	com/google/android/common/base/StringUtil:ESCAPE_STRINGS	Ljava/util/Map;
    //   8027: wide
    //   8031: sipush 8217
    //   8034: invokestatic 89	java/lang/Character:valueOf	(C)Ljava/lang/Character;
    //   8037: wide
    //   8041: wide
    //   8045: ldc_w 579
    //   8048: wide
    //   8052: invokeinterface 97 3 0
    //   8057: wide
    //   8061: getstatic 83	com/google/android/common/base/StringUtil:ESCAPE_STRINGS	Ljava/util/Map;
    //   8064: wide
    //   8068: sipush 8218
    //   8071: invokestatic 89	java/lang/Character:valueOf	(C)Ljava/lang/Character;
    //   8074: wide
    //   8078: wide
    //   8082: ldc_w 581
    //   8085: wide
    //   8089: invokeinterface 97 3 0
    //   8094: wide
    //   8098: getstatic 83	com/google/android/common/base/StringUtil:ESCAPE_STRINGS	Ljava/util/Map;
    //   8101: wide
    //   8105: sipush 8220
    //   8108: invokestatic 89	java/lang/Character:valueOf	(C)Ljava/lang/Character;
    //   8111: wide
    //   8115: wide
    //   8119: ldc_w 583
    //   8122: wide
    //   8126: invokeinterface 97 3 0
    //   8131: wide
    //   8135: getstatic 83	com/google/android/common/base/StringUtil:ESCAPE_STRINGS	Ljava/util/Map;
    //   8138: wide
    //   8142: sipush 8221
    //   8145: invokestatic 89	java/lang/Character:valueOf	(C)Ljava/lang/Character;
    //   8148: wide
    //   8152: wide
    //   8156: ldc_w 585
    //   8159: wide
    //   8163: invokeinterface 97 3 0
    //   8168: wide
    //   8172: getstatic 83	com/google/android/common/base/StringUtil:ESCAPE_STRINGS	Ljava/util/Map;
    //   8175: wide
    //   8179: sipush 8222
    //   8182: invokestatic 89	java/lang/Character:valueOf	(C)Ljava/lang/Character;
    //   8185: wide
    //   8189: wide
    //   8193: ldc_w 587
    //   8196: wide
    //   8200: invokeinterface 97 3 0
    //   8205: wide
    //   8209: getstatic 83	com/google/android/common/base/StringUtil:ESCAPE_STRINGS	Ljava/util/Map;
    //   8212: wide
    //   8216: sipush 8224
    //   8219: invokestatic 89	java/lang/Character:valueOf	(C)Ljava/lang/Character;
    //   8222: wide
    //   8226: wide
    //   8230: ldc_w 589
    //   8233: wide
    //   8237: invokeinterface 97 3 0
    //   8242: wide
    //   8246: getstatic 83	com/google/android/common/base/StringUtil:ESCAPE_STRINGS	Ljava/util/Map;
    //   8249: wide
    //   8253: sipush 8225
    //   8256: invokestatic 89	java/lang/Character:valueOf	(C)Ljava/lang/Character;
    //   8259: wide
    //   8263: wide
    //   8267: ldc_w 591
    //   8270: wide
    //   8274: invokeinterface 97 3 0
    //   8279: wide
    //   8283: getstatic 83	com/google/android/common/base/StringUtil:ESCAPE_STRINGS	Ljava/util/Map;
    //   8286: wide
    //   8290: sipush 8240
    //   8293: invokestatic 89	java/lang/Character:valueOf	(C)Ljava/lang/Character;
    //   8296: wide
    //   8300: wide
    //   8304: ldc_w 593
    //   8307: wide
    //   8311: invokeinterface 97 3 0
    //   8316: wide
    //   8320: getstatic 83	com/google/android/common/base/StringUtil:ESCAPE_STRINGS	Ljava/util/Map;
    //   8323: wide
    //   8327: sipush 8249
    //   8330: invokestatic 89	java/lang/Character:valueOf	(C)Ljava/lang/Character;
    //   8333: wide
    //   8337: wide
    //   8341: ldc_w 595
    //   8344: wide
    //   8348: invokeinterface 97 3 0
    //   8353: wide
    //   8357: getstatic 83	com/google/android/common/base/StringUtil:ESCAPE_STRINGS	Ljava/util/Map;
    //   8360: wide
    //   8364: sipush 8250
    //   8367: invokestatic 89	java/lang/Character:valueOf	(C)Ljava/lang/Character;
    //   8370: wide
    //   8374: wide
    //   8378: ldc_w 597
    //   8381: wide
    //   8385: invokeinterface 97 3 0
    //   8390: wide
    //   8394: getstatic 83	com/google/android/common/base/StringUtil:ESCAPE_STRINGS	Ljava/util/Map;
    //   8397: wide
    //   8401: sipush 8364
    //   8404: invokestatic 89	java/lang/Character:valueOf	(C)Ljava/lang/Character;
    //   8407: wide
    //   8411: wide
    //   8415: ldc_w 599
    //   8418: wide
    //   8422: invokeinterface 97 3 0
    //   8427: wide
    //   8431: new 601	java/util/HashSet
    //   8434: dup
    //   8435: bipush 12
    //   8437: invokespecial 602	java/util/HashSet:<init>	(I)V
    //   8440: putstatic 604	com/google/android/common/base/StringUtil:HEX_LETTERS	Ljava/util/Set;
    //   8443: getstatic 604	com/google/android/common/base/StringUtil:HEX_LETTERS	Ljava/util/Set;
    //   8446: wide
    //   8450: bipush 97
    //   8452: invokestatic 89	java/lang/Character:valueOf	(C)Ljava/lang/Character;
    //   8455: wide
    //   8459: wide
    //   8463: wide
    //   8467: invokeinterface 610 2 0
    //   8472: wide
    //   8476: getstatic 604	com/google/android/common/base/StringUtil:HEX_LETTERS	Ljava/util/Set;
    //   8479: wide
    //   8483: bipush 65
    //   8485: invokestatic 89	java/lang/Character:valueOf	(C)Ljava/lang/Character;
    //   8488: wide
    //   8492: wide
    //   8496: wide
    //   8500: invokeinterface 610 2 0
    //   8505: wide
    //   8509: getstatic 604	com/google/android/common/base/StringUtil:HEX_LETTERS	Ljava/util/Set;
    //   8512: wide
    //   8516: bipush 98
    //   8518: invokestatic 89	java/lang/Character:valueOf	(C)Ljava/lang/Character;
    //   8521: wide
    //   8525: wide
    //   8529: wide
    //   8533: invokeinterface 610 2 0
    //   8538: wide
    //   8542: getstatic 604	com/google/android/common/base/StringUtil:HEX_LETTERS	Ljava/util/Set;
    //   8545: wide
    //   8549: bipush 66
    //   8551: invokestatic 89	java/lang/Character:valueOf	(C)Ljava/lang/Character;
    //   8554: wide
    //   8558: wide
    //   8562: wide
    //   8566: invokeinterface 610 2 0
    //   8571: wide
    //   8575: getstatic 604	com/google/android/common/base/StringUtil:HEX_LETTERS	Ljava/util/Set;
    //   8578: wide
    //   8582: bipush 99
    //   8584: invokestatic 89	java/lang/Character:valueOf	(C)Ljava/lang/Character;
    //   8587: wide
    //   8591: wide
    //   8595: wide
    //   8599: invokeinterface 610 2 0
    //   8604: wide
    //   8608: getstatic 604	com/google/android/common/base/StringUtil:HEX_LETTERS	Ljava/util/Set;
    //   8611: wide
    //   8615: bipush 67
    //   8617: invokestatic 89	java/lang/Character:valueOf	(C)Ljava/lang/Character;
    //   8620: wide
    //   8624: wide
    //   8628: wide
    //   8632: invokeinterface 610 2 0
    //   8637: wide
    //   8641: getstatic 604	com/google/android/common/base/StringUtil:HEX_LETTERS	Ljava/util/Set;
    //   8644: wide
    //   8648: bipush 100
    //   8650: invokestatic 89	java/lang/Character:valueOf	(C)Ljava/lang/Character;
    //   8653: wide
    //   8657: wide
    //   8661: wide
    //   8665: invokeinterface 610 2 0
    //   8670: wide
    //   8674: getstatic 604	com/google/android/common/base/StringUtil:HEX_LETTERS	Ljava/util/Set;
    //   8677: wide
    //   8681: bipush 68
    //   8683: invokestatic 89	java/lang/Character:valueOf	(C)Ljava/lang/Character;
    //   8686: wide
    //   8690: wide
    //   8694: wide
    //   8698: invokeinterface 610 2 0
    //   8703: wide
    //   8707: getstatic 604	com/google/android/common/base/StringUtil:HEX_LETTERS	Ljava/util/Set;
    //   8710: wide
    //   8714: bipush 101
    //   8716: invokestatic 89	java/lang/Character:valueOf	(C)Ljava/lang/Character;
    //   8719: wide
    //   8723: wide
    //   8727: wide
    //   8731: invokeinterface 610 2 0
    //   8736: wide
    //   8740: getstatic 604	com/google/android/common/base/StringUtil:HEX_LETTERS	Ljava/util/Set;
    //   8743: wide
    //   8747: bipush 69
    //   8749: invokestatic 89	java/lang/Character:valueOf	(C)Ljava/lang/Character;
    //   8752: wide
    //   8756: wide
    //   8760: wide
    //   8764: invokeinterface 610 2 0
    //   8769: wide
    //   8773: getstatic 604	com/google/android/common/base/StringUtil:HEX_LETTERS	Ljava/util/Set;
    //   8776: wide
    //   8780: bipush 102
    //   8782: invokestatic 89	java/lang/Character:valueOf	(C)Ljava/lang/Character;
    //   8785: wide
    //   8789: wide
    //   8793: wide
    //   8797: invokeinterface 610 2 0
    //   8802: wide
    //   8806: getstatic 604	com/google/android/common/base/StringUtil:HEX_LETTERS	Ljava/util/Set;
    //   8809: wide
    //   8813: bipush 70
    //   8815: invokestatic 89	java/lang/Character:valueOf	(C)Ljava/lang/Character;
    //   8818: wide
    //   8822: wide
    //   8826: wide
    //   8830: invokeinterface 610 2 0
    //   8835: wide
    //   8839: new 612	com/google/android/common/base/CharEscaperBuilder
    //   8842: dup
    //   8843: invokespecial 614	com/google/android/common/base/CharEscaperBuilder:<init>	()V
    //   8846: bipush 60
    //   8848: ldc_w 616
    //   8851: invokevirtual 620	com/google/android/common/base/CharEscaperBuilder:addEscape	(CLjava/lang/String;)Lcom/google/android/common/base/CharEscaperBuilder;
    //   8854: bipush 62
    //   8856: ldc_w 622
    //   8859: invokevirtual 620	com/google/android/common/base/CharEscaperBuilder:addEscape	(CLjava/lang/String;)Lcom/google/android/common/base/CharEscaperBuilder;
    //   8862: invokevirtual 626	com/google/android/common/base/CharEscaperBuilder:toEscaper	()Lcom/google/android/common/base/CharEscaper;
    //   8865: putstatic 628	com/google/android/common/base/StringUtil:LT_GT_ESCAPE	Lcom/google/android/common/base/CharEscaper;
    //   8868: ldc_w 630
    //   8871: invokestatic 636	java/util/regex/Pattern:compile	(Ljava/lang/String;)Ljava/util/regex/Pattern;
    //   8874: putstatic 638	com/google/android/common/base/StringUtil:htmlTagPattern	Ljava/util/regex/Pattern;
    //   8877: ldc_w 640
    //   8880: invokestatic 69	com/google/android/common/base/CharMatcher:anyOf	(Ljava/lang/CharSequence;)Lcom/google/android/common/base/CharMatcher;
    //   8883: putstatic 642	com/google/android/common/base/StringUtil:CONTROL_MATCHER	Lcom/google/android/common/base/CharMatcher;
    //   8886: new 612	com/google/android/common/base/CharEscaperBuilder
    //   8889: dup
    //   8890: invokespecial 614	com/google/android/common/base/CharEscaperBuilder:<init>	()V
    //   8893: bipush 10
    //   8895: ldc_w 644
    //   8898: invokevirtual 620	com/google/android/common/base/CharEscaperBuilder:addEscape	(CLjava/lang/String;)Lcom/google/android/common/base/CharEscaperBuilder;
    //   8901: bipush 13
    //   8903: ldc_w 646
    //   8906: invokevirtual 620	com/google/android/common/base/CharEscaperBuilder:addEscape	(CLjava/lang/String;)Lcom/google/android/common/base/CharEscaperBuilder;
    //   8909: bipush 9
    //   8911: ldc_w 648
    //   8914: invokevirtual 620	com/google/android/common/base/CharEscaperBuilder:addEscape	(CLjava/lang/String;)Lcom/google/android/common/base/CharEscaperBuilder;
    //   8917: bipush 92
    //   8919: ldc_w 650
    //   8922: invokevirtual 620	com/google/android/common/base/CharEscaperBuilder:addEscape	(CLjava/lang/String;)Lcom/google/android/common/base/CharEscaperBuilder;
    //   8925: bipush 34
    //   8927: ldc_w 652
    //   8930: invokevirtual 620	com/google/android/common/base/CharEscaperBuilder:addEscape	(CLjava/lang/String;)Lcom/google/android/common/base/CharEscaperBuilder;
    //   8933: bipush 38
    //   8935: ldc_w 654
    //   8938: invokevirtual 620	com/google/android/common/base/CharEscaperBuilder:addEscape	(CLjava/lang/String;)Lcom/google/android/common/base/CharEscaperBuilder;
    //   8941: bipush 60
    //   8943: ldc_w 616
    //   8946: invokevirtual 620	com/google/android/common/base/CharEscaperBuilder:addEscape	(CLjava/lang/String;)Lcom/google/android/common/base/CharEscaperBuilder;
    //   8949: bipush 62
    //   8951: ldc_w 622
    //   8954: invokevirtual 620	com/google/android/common/base/CharEscaperBuilder:addEscape	(CLjava/lang/String;)Lcom/google/android/common/base/CharEscaperBuilder;
    //   8957: bipush 39
    //   8959: ldc_w 656
    //   8962: invokevirtual 620	com/google/android/common/base/CharEscaperBuilder:addEscape	(CLjava/lang/String;)Lcom/google/android/common/base/CharEscaperBuilder;
    //   8965: invokevirtual 626	com/google/android/common/base/CharEscaperBuilder:toEscaper	()Lcom/google/android/common/base/CharEscaper;
    //   8968: putstatic 658	com/google/android/common/base/StringUtil:JAVA_ESCAPE	Lcom/google/android/common/base/CharEscaper;
    //   8971: new 612	com/google/android/common/base/CharEscaperBuilder
    //   8974: dup
    //   8975: invokespecial 614	com/google/android/common/base/CharEscaperBuilder:<init>	()V
    //   8978: bipush 40
    //   8980: ldc_w 660
    //   8983: invokevirtual 620	com/google/android/common/base/CharEscaperBuilder:addEscape	(CLjava/lang/String;)Lcom/google/android/common/base/CharEscaperBuilder;
    //   8986: bipush 41
    //   8988: ldc_w 662
    //   8991: invokevirtual 620	com/google/android/common/base/CharEscaperBuilder:addEscape	(CLjava/lang/String;)Lcom/google/android/common/base/CharEscaperBuilder;
    //   8994: bipush 124
    //   8996: ldc_w 664
    //   8999: invokevirtual 620	com/google/android/common/base/CharEscaperBuilder:addEscape	(CLjava/lang/String;)Lcom/google/android/common/base/CharEscaperBuilder;
    //   9002: bipush 42
    //   9004: ldc_w 666
    //   9007: invokevirtual 620	com/google/android/common/base/CharEscaperBuilder:addEscape	(CLjava/lang/String;)Lcom/google/android/common/base/CharEscaperBuilder;
    //   9010: bipush 43
    //   9012: ldc_w 668
    //   9015: invokevirtual 620	com/google/android/common/base/CharEscaperBuilder:addEscape	(CLjava/lang/String;)Lcom/google/android/common/base/CharEscaperBuilder;
    //   9018: bipush 63
    //   9020: ldc_w 670
    //   9023: invokevirtual 620	com/google/android/common/base/CharEscaperBuilder:addEscape	(CLjava/lang/String;)Lcom/google/android/common/base/CharEscaperBuilder;
    //   9026: bipush 46
    //   9028: ldc_w 672
    //   9031: invokevirtual 620	com/google/android/common/base/CharEscaperBuilder:addEscape	(CLjava/lang/String;)Lcom/google/android/common/base/CharEscaperBuilder;
    //   9034: bipush 123
    //   9036: ldc_w 674
    //   9039: invokevirtual 620	com/google/android/common/base/CharEscaperBuilder:addEscape	(CLjava/lang/String;)Lcom/google/android/common/base/CharEscaperBuilder;
    //   9042: bipush 125
    //   9044: ldc_w 676
    //   9047: invokevirtual 620	com/google/android/common/base/CharEscaperBuilder:addEscape	(CLjava/lang/String;)Lcom/google/android/common/base/CharEscaperBuilder;
    //   9050: bipush 91
    //   9052: ldc_w 678
    //   9055: invokevirtual 620	com/google/android/common/base/CharEscaperBuilder:addEscape	(CLjava/lang/String;)Lcom/google/android/common/base/CharEscaperBuilder;
    //   9058: bipush 93
    //   9060: ldc_w 680
    //   9063: invokevirtual 620	com/google/android/common/base/CharEscaperBuilder:addEscape	(CLjava/lang/String;)Lcom/google/android/common/base/CharEscaperBuilder;
    //   9066: bipush 36
    //   9068: ldc_w 682
    //   9071: invokevirtual 620	com/google/android/common/base/CharEscaperBuilder:addEscape	(CLjava/lang/String;)Lcom/google/android/common/base/CharEscaperBuilder;
    //   9074: bipush 94
    //   9076: ldc_w 684
    //   9079: invokevirtual 620	com/google/android/common/base/CharEscaperBuilder:addEscape	(CLjava/lang/String;)Lcom/google/android/common/base/CharEscaperBuilder;
    //   9082: bipush 92
    //   9084: ldc_w 650
    //   9087: invokevirtual 620	com/google/android/common/base/CharEscaperBuilder:addEscape	(CLjava/lang/String;)Lcom/google/android/common/base/CharEscaperBuilder;
    //   9090: invokevirtual 626	com/google/android/common/base/CharEscaperBuilder:toEscaper	()Lcom/google/android/common/base/CharEscaper;
    //   9093: putstatic 686	com/google/android/common/base/StringUtil:REGEX_ESCAPE	Lcom/google/android/common/base/CharEscaper;
    //   9096: ldc_w 688
    //   9099: invokestatic 636	java/util/regex/Pattern:compile	(Ljava/lang/String;)Ljava/util/regex/Pattern;
    //   9102: putstatic 690	com/google/android/common/base/StringUtil:characterReferencePattern	Ljava/util/regex/Pattern;
    //   9105: new 601	java/util/HashSet
    //   9108: dup
    //   9109: invokespecial 691	java/util/HashSet:<init>	()V
    //   9112: wide
    //   9116: getstatic 697	java/lang/Character$UnicodeBlock:HANGUL_JAMO	Ljava/lang/Character$UnicodeBlock;
    //   9119: wide
    //   9123: wide
    //   9127: wide
    //   9131: invokeinterface 610 2 0
    //   9136: wide
    //   9140: getstatic 700	java/lang/Character$UnicodeBlock:CJK_RADICALS_SUPPLEMENT	Ljava/lang/Character$UnicodeBlock;
    //   9143: wide
    //   9147: wide
    //   9151: wide
    //   9155: invokeinterface 610 2 0
    //   9160: wide
    //   9164: getstatic 703	java/lang/Character$UnicodeBlock:KANGXI_RADICALS	Ljava/lang/Character$UnicodeBlock;
    //   9167: wide
    //   9171: wide
    //   9175: wide
    //   9179: invokeinterface 610 2 0
    //   9184: wide
    //   9188: getstatic 706	java/lang/Character$UnicodeBlock:CJK_SYMBOLS_AND_PUNCTUATION	Ljava/lang/Character$UnicodeBlock;
    //   9191: wide
    //   9195: wide
    //   9199: wide
    //   9203: invokeinterface 610 2 0
    //   9208: wide
    //   9212: getstatic 709	java/lang/Character$UnicodeBlock:HIRAGANA	Ljava/lang/Character$UnicodeBlock;
    //   9215: wide
    //   9219: wide
    //   9223: wide
    //   9227: invokeinterface 610 2 0
    //   9232: wide
    //   9236: getstatic 712	java/lang/Character$UnicodeBlock:KATAKANA	Ljava/lang/Character$UnicodeBlock;
    //   9239: wide
    //   9243: wide
    //   9247: wide
    //   9251: invokeinterface 610 2 0
    //   9256: wide
    //   9260: getstatic 715	java/lang/Character$UnicodeBlock:BOPOMOFO	Ljava/lang/Character$UnicodeBlock;
    //   9263: wide
    //   9267: wide
    //   9271: wide
    //   9275: invokeinterface 610 2 0
    //   9280: wide
    //   9284: getstatic 718	java/lang/Character$UnicodeBlock:HANGUL_COMPATIBILITY_JAMO	Ljava/lang/Character$UnicodeBlock;
    //   9287: wide
    //   9291: wide
    //   9295: wide
    //   9299: invokeinterface 610 2 0
    //   9304: wide
    //   9308: getstatic 721	java/lang/Character$UnicodeBlock:KANBUN	Ljava/lang/Character$UnicodeBlock;
    //   9311: wide
    //   9315: wide
    //   9319: wide
    //   9323: invokeinterface 610 2 0
    //   9328: wide
    //   9332: getstatic 724	java/lang/Character$UnicodeBlock:BOPOMOFO_EXTENDED	Ljava/lang/Character$UnicodeBlock;
    //   9335: wide
    //   9339: wide
    //   9343: wide
    //   9347: invokeinterface 610 2 0
    //   9352: wide
    //   9356: getstatic 727	java/lang/Character$UnicodeBlock:KATAKANA_PHONETIC_EXTENSIONS	Ljava/lang/Character$UnicodeBlock;
    //   9359: wide
    //   9363: wide
    //   9367: wide
    //   9371: invokeinterface 610 2 0
    //   9376: wide
    //   9380: getstatic 730	java/lang/Character$UnicodeBlock:ENCLOSED_CJK_LETTERS_AND_MONTHS	Ljava/lang/Character$UnicodeBlock;
    //   9383: wide
    //   9387: wide
    //   9391: wide
    //   9395: invokeinterface 610 2 0
    //   9400: wide
    //   9404: getstatic 733	java/lang/Character$UnicodeBlock:CJK_COMPATIBILITY	Ljava/lang/Character$UnicodeBlock;
    //   9407: wide
    //   9411: wide
    //   9415: wide
    //   9419: invokeinterface 610 2 0
    //   9424: wide
    //   9428: getstatic 736	java/lang/Character$UnicodeBlock:CJK_UNIFIED_IDEOGRAPHS_EXTENSION_A	Ljava/lang/Character$UnicodeBlock;
    //   9431: wide
    //   9435: wide
    //   9439: wide
    //   9443: invokeinterface 610 2 0
    //   9448: wide
    //   9452: getstatic 739	java/lang/Character$UnicodeBlock:CJK_UNIFIED_IDEOGRAPHS	Ljava/lang/Character$UnicodeBlock;
    //   9455: wide
    //   9459: wide
    //   9463: wide
    //   9467: invokeinterface 610 2 0
    //   9472: wide
    //   9476: getstatic 742	java/lang/Character$UnicodeBlock:HANGUL_SYLLABLES	Ljava/lang/Character$UnicodeBlock;
    //   9479: wide
    //   9483: wide
    //   9487: wide
    //   9491: invokeinterface 610 2 0
    //   9496: wide
    //   9500: getstatic 745	java/lang/Character$UnicodeBlock:CJK_COMPATIBILITY_IDEOGRAPHS	Ljava/lang/Character$UnicodeBlock;
    //   9503: wide
    //   9507: wide
    //   9511: wide
    //   9515: invokeinterface 610 2 0
    //   9520: wide
    //   9524: getstatic 748	java/lang/Character$UnicodeBlock:CJK_COMPATIBILITY_FORMS	Ljava/lang/Character$UnicodeBlock;
    //   9527: wide
    //   9531: wide
    //   9535: wide
    //   9539: invokeinterface 610 2 0
    //   9544: wide
    //   9548: getstatic 751	java/lang/Character$UnicodeBlock:HALFWIDTH_AND_FULLWIDTH_FORMS	Ljava/lang/Character$UnicodeBlock;
    //   9551: wide
    //   9555: wide
    //   9559: wide
    //   9563: invokeinterface 610 2 0
    //   9568: wide
    //   9572: getstatic 754	java/lang/Character$UnicodeBlock:CJK_UNIFIED_IDEOGRAPHS_EXTENSION_B	Ljava/lang/Character$UnicodeBlock;
    //   9575: wide
    //   9579: wide
    //   9583: wide
    //   9587: invokeinterface 610 2 0
    //   9592: wide
    //   9596: getstatic 757	java/lang/Character$UnicodeBlock:CJK_COMPATIBILITY_IDEOGRAPHS_SUPPLEMENT	Ljava/lang/Character$UnicodeBlock;
    //   9599: wide
    //   9603: wide
    //   9607: wide
    //   9611: invokeinterface 610 2 0
    //   9616: wide
    //   9620: wide
    //   9624: invokestatic 763	java/util/Collections:unmodifiableSet	(Ljava/util/Set;)Ljava/util/Set;
    //   9627: putstatic 765	com/google/android/common/base/StringUtil:CJK_BLOCKS	Ljava/util/Set;
    //   9630: bipush 16
    //   9632: newarray char
    //   9634: dup
    //   9635: iconst_0
    //   9636: ldc_w 766
    //   9639: sastore
    //   9640: dup
    //   9641: iconst_1
    //   9642: ldc_w 767
    //   9645: sastore
    //   9646: dup
    //   9647: iconst_2
    //   9648: ldc_w 768
    //   9651: sastore
    //   9652: dup
    //   9653: iconst_3
    //   9654: ldc_w 769
    //   9657: sastore
    //   9658: dup
    //   9659: iconst_4
    //   9660: ldc_w 770
    //   9663: sastore
    //   9664: dup
    //   9665: iconst_5
    //   9666: ldc_w 771
    //   9669: sastore
    //   9670: dup
    //   9671: bipush 6
    //   9673: ldc_w 772
    //   9676: sastore
    //   9677: dup
    //   9678: bipush 7
    //   9680: ldc_w 773
    //   9683: sastore
    //   9684: dup
    //   9685: bipush 8
    //   9687: ldc_w 774
    //   9690: sastore
    //   9691: dup
    //   9692: bipush 9
    //   9694: ldc_w 775
    //   9697: sastore
    //   9698: dup
    //   9699: bipush 10
    //   9701: ldc_w 776
    //   9704: sastore
    //   9705: dup
    //   9706: bipush 11
    //   9708: ldc_w 777
    //   9711: sastore
    //   9712: dup
    //   9713: bipush 12
    //   9715: ldc_w 778
    //   9718: sastore
    //   9719: dup
    //   9720: bipush 13
    //   9722: ldc_w 779
    //   9725: sastore
    //   9726: dup
    //   9727: bipush 14
    //   9729: ldc_w 780
    //   9732: sastore
    //   9733: dup
    //   9734: bipush 15
    //   9736: ldc_w 781
    //   9739: sastore
    //   9740: putstatic 783	com/google/android/common/base/StringUtil:HEX_CHARS	[C
    //   9743: getstatic 783	com/google/android/common/base/StringUtil:HEX_CHARS	[C
    //   9746: putstatic 785	com/google/android/common/base/StringUtil:OCTAL_CHARS	[C
    //   9749: ldc_w 787
    //   9752: invokestatic 636	java/util/regex/Pattern:compile	(Ljava/lang/String;)Ljava/util/regex/Pattern;
    //   9755: putstatic 789	com/google/android/common/base/StringUtil:dbSpecPattern	Ljava/util/regex/Pattern;
    //   9758: new 8	com/google/android/common/base/StringUtil$UnicodeSetBuilder
    //   9761: dup
    //   9762: aconst_null
    //   9763: invokespecial 792	com/google/android/common/base/StringUtil$UnicodeSetBuilder:<init>	(Lcom/google/android/common/base/StringUtil$1;)V
    //   9766: sipush 173
    //   9769: invokevirtual 796	com/google/android/common/base/StringUtil$UnicodeSetBuilder:addCodePoint	(I)Lcom/google/android/common/base/StringUtil$UnicodeSetBuilder;
    //   9772: sipush 1536
    //   9775: sipush 1539
    //   9778: invokevirtual 800	com/google/android/common/base/StringUtil$UnicodeSetBuilder:addRange	(II)Lcom/google/android/common/base/StringUtil$UnicodeSetBuilder;
    //   9781: sipush 1757
    //   9784: invokevirtual 796	com/google/android/common/base/StringUtil$UnicodeSetBuilder:addCodePoint	(I)Lcom/google/android/common/base/StringUtil$UnicodeSetBuilder;
    //   9787: sipush 1807
    //   9790: invokevirtual 796	com/google/android/common/base/StringUtil$UnicodeSetBuilder:addCodePoint	(I)Lcom/google/android/common/base/StringUtil$UnicodeSetBuilder;
    //   9793: sipush 6068
    //   9796: sipush 6069
    //   9799: invokevirtual 800	com/google/android/common/base/StringUtil$UnicodeSetBuilder:addRange	(II)Lcom/google/android/common/base/StringUtil$UnicodeSetBuilder;
    //   9802: sipush 8203
    //   9805: sipush 8207
    //   9808: invokevirtual 800	com/google/android/common/base/StringUtil$UnicodeSetBuilder:addRange	(II)Lcom/google/android/common/base/StringUtil$UnicodeSetBuilder;
    //   9811: sipush 8234
    //   9814: sipush 8238
    //   9817: invokevirtual 800	com/google/android/common/base/StringUtil$UnicodeSetBuilder:addRange	(II)Lcom/google/android/common/base/StringUtil$UnicodeSetBuilder;
    //   9820: sipush 8288
    //   9823: sipush 8292
    //   9826: invokevirtual 800	com/google/android/common/base/StringUtil$UnicodeSetBuilder:addRange	(II)Lcom/google/android/common/base/StringUtil$UnicodeSetBuilder;
    //   9829: sipush 8298
    //   9832: sipush 8303
    //   9835: invokevirtual 800	com/google/android/common/base/StringUtil$UnicodeSetBuilder:addRange	(II)Lcom/google/android/common/base/StringUtil$UnicodeSetBuilder;
    //   9838: ldc_w 801
    //   9841: invokevirtual 796	com/google/android/common/base/StringUtil$UnicodeSetBuilder:addCodePoint	(I)Lcom/google/android/common/base/StringUtil$UnicodeSetBuilder;
    //   9844: ldc_w 802
    //   9847: ldc_w 803
    //   9850: invokevirtual 800	com/google/android/common/base/StringUtil$UnicodeSetBuilder:addRange	(II)Lcom/google/android/common/base/StringUtil$UnicodeSetBuilder;
    //   9853: ldc_w 804
    //   9856: ldc_w 805
    //   9859: invokevirtual 800	com/google/android/common/base/StringUtil$UnicodeSetBuilder:addRange	(II)Lcom/google/android/common/base/StringUtil$UnicodeSetBuilder;
    //   9862: ldc_w 806
    //   9865: invokevirtual 796	com/google/android/common/base/StringUtil$UnicodeSetBuilder:addCodePoint	(I)Lcom/google/android/common/base/StringUtil$UnicodeSetBuilder;
    //   9868: ldc_w 807
    //   9871: ldc_w 808
    //   9874: invokevirtual 800	com/google/android/common/base/StringUtil$UnicodeSetBuilder:addRange	(II)Lcom/google/android/common/base/StringUtil$UnicodeSetBuilder;
    //   9877: iconst_0
    //   9878: invokevirtual 796	com/google/android/common/base/StringUtil$UnicodeSetBuilder:addCodePoint	(I)Lcom/google/android/common/base/StringUtil$UnicodeSetBuilder;
    //   9881: bipush 10
    //   9883: invokevirtual 796	com/google/android/common/base/StringUtil$UnicodeSetBuilder:addCodePoint	(I)Lcom/google/android/common/base/StringUtil$UnicodeSetBuilder;
    //   9886: bipush 13
    //   9888: invokevirtual 796	com/google/android/common/base/StringUtil$UnicodeSetBuilder:addCodePoint	(I)Lcom/google/android/common/base/StringUtil$UnicodeSetBuilder;
    //   9891: sipush 8232
    //   9894: sipush 8233
    //   9897: invokevirtual 800	com/google/android/common/base/StringUtil$UnicodeSetBuilder:addRange	(II)Lcom/google/android/common/base/StringUtil$UnicodeSetBuilder;
    //   9900: sipush 133
    //   9903: invokevirtual 796	com/google/android/common/base/StringUtil$UnicodeSetBuilder:addCodePoint	(I)Lcom/google/android/common/base/StringUtil$UnicodeSetBuilder;
    //   9906: wide
    //   9910: ldc_w 810
    //   9913: iconst_0
    //   9914: invokestatic 814	java/lang/Character:codePointAt	(Ljava/lang/CharSequence;I)I
    //   9917: wide
    //   9921: wide
    //   9925: wide
    //   9929: invokevirtual 796	com/google/android/common/base/StringUtil$UnicodeSetBuilder:addCodePoint	(I)Lcom/google/android/common/base/StringUtil$UnicodeSetBuilder;
    //   9932: wide
    //   9936: ldc_w 816
    //   9939: iconst_0
    //   9940: invokestatic 814	java/lang/Character:codePointAt	(Ljava/lang/CharSequence;I)I
    //   9943: wide
    //   9947: wide
    //   9951: wide
    //   9955: invokevirtual 796	com/google/android/common/base/StringUtil$UnicodeSetBuilder:addCodePoint	(I)Lcom/google/android/common/base/StringUtil$UnicodeSetBuilder;
    //   9958: wide
    //   9962: ldc_w 818
    //   9965: iconst_0
    //   9966: invokestatic 814	java/lang/Character:codePointAt	(Ljava/lang/CharSequence;I)I
    //   9969: wide
    //   9973: wide
    //   9977: wide
    //   9981: invokevirtual 796	com/google/android/common/base/StringUtil$UnicodeSetBuilder:addCodePoint	(I)Lcom/google/android/common/base/StringUtil$UnicodeSetBuilder;
    //   9984: wide
    //   9988: ldc_w 820
    //   9991: iconst_0
    //   9992: invokestatic 814	java/lang/Character:codePointAt	(Ljava/lang/CharSequence;I)I
    //   9995: wide
    //   9999: wide
    //   10003: wide
    //   10007: invokevirtual 796	com/google/android/common/base/StringUtil$UnicodeSetBuilder:addCodePoint	(I)Lcom/google/android/common/base/StringUtil$UnicodeSetBuilder;
    //   10010: wide
    //   10014: ldc_w 822
    //   10017: iconst_0
    //   10018: invokestatic 814	java/lang/Character:codePointAt	(Ljava/lang/CharSequence;I)I
    //   10021: wide
    //   10025: wide
    //   10029: wide
    //   10033: invokevirtual 796	com/google/android/common/base/StringUtil$UnicodeSetBuilder:addCodePoint	(I)Lcom/google/android/common/base/StringUtil$UnicodeSetBuilder;
    //   10036: wide
    //   10040: ldc_w 824
    //   10043: iconst_0
    //   10044: invokestatic 814	java/lang/Character:codePointAt	(Ljava/lang/CharSequence;I)I
    //   10047: wide
    //   10051: wide
    //   10055: wide
    //   10059: invokevirtual 796	com/google/android/common/base/StringUtil$UnicodeSetBuilder:addCodePoint	(I)Lcom/google/android/common/base/StringUtil$UnicodeSetBuilder;
    //   10062: wide
    //   10066: ldc_w 826
    //   10069: iconst_0
    //   10070: invokestatic 814	java/lang/Character:codePointAt	(Ljava/lang/CharSequence;I)I
    //   10073: wide
    //   10077: wide
    //   10081: wide
    //   10085: invokevirtual 796	com/google/android/common/base/StringUtil$UnicodeSetBuilder:addCodePoint	(I)Lcom/google/android/common/base/StringUtil$UnicodeSetBuilder;
    //   10088: invokevirtual 830	com/google/android/common/base/StringUtil$UnicodeSetBuilder:create	()Ljava/util/Set;
    //   10091: putstatic 832	com/google/android/common/base/StringUtil:JS_ESCAPE_CHARS	Ljava/util/Set;
    //   10094: new 8	com/google/android/common/base/StringUtil$UnicodeSetBuilder
    //   10097: dup
    //   10098: aconst_null
    //   10099: invokespecial 792	com/google/android/common/base/StringUtil$UnicodeSetBuilder:<init>	(Lcom/google/android/common/base/StringUtil$1;)V
    //   10102: wide
    //   10106: ldc_w 816
    //   10109: iconst_0
    //   10110: invokestatic 814	java/lang/Character:codePointAt	(Ljava/lang/CharSequence;I)I
    //   10113: wide
    //   10117: wide
    //   10121: wide
    //   10125: invokevirtual 796	com/google/android/common/base/StringUtil$UnicodeSetBuilder:addCodePoint	(I)Lcom/google/android/common/base/StringUtil$UnicodeSetBuilder;
    //   10128: wide
    //   10132: ldc_w 826
    //   10135: iconst_0
    //   10136: invokestatic 814	java/lang/Character:codePointAt	(Ljava/lang/CharSequence;I)I
    //   10139: wide
    //   10143: wide
    //   10147: wide
    //   10151: invokevirtual 796	com/google/android/common/base/StringUtil$UnicodeSetBuilder:addCodePoint	(I)Lcom/google/android/common/base/StringUtil$UnicodeSetBuilder;
    //   10154: iconst_0
    //   10155: bipush 31
    //   10157: invokevirtual 800	com/google/android/common/base/StringUtil$UnicodeSetBuilder:addRange	(II)Lcom/google/android/common/base/StringUtil$UnicodeSetBuilder;
    //   10160: invokevirtual 830	com/google/android/common/base/StringUtil$UnicodeSetBuilder:create	()Ljava/util/Set;
    //   10163: putstatic 834	com/google/android/common/base/StringUtil:JSON_ESCAPE_CHARS	Ljava/util/Set;
    //   10166: return
  }

  public static String truncateAtMaxLength(String paramString, int paramInt, boolean paramBoolean)
  {
    if (paramString.length() <= paramInt);
    while (true)
    {
      return paramString;
      if ((paramBoolean) && (paramInt > 3))
      {
        StringBuilder localStringBuilder = new StringBuilder();
        int i = paramInt + -3;
        String str = unicodePreservingSubstring(paramString, 0, i);
        paramString = str + "...";
      }
      else
      {
        paramString = unicodePreservingSubstring(paramString, 0, paramInt);
      }
    }
  }

  public static int unicodePreservingIndex(String paramString, int paramInt)
  {
    if (paramInt > 0)
    {
      int i = paramString.length();
      if (paramInt < i)
      {
        int j = paramInt + -1;
        if ((Character.isHighSurrogate(paramString.charAt(j))) && (Character.isLowSurrogate(paramString.charAt(paramInt))))
          paramInt += -1;
      }
    }
    return paramInt;
  }

  public static String unicodePreservingSubstring(String paramString, int paramInt1, int paramInt2)
  {
    int i = unicodePreservingIndex(paramString, paramInt1);
    int j = unicodePreservingIndex(paramString, paramInt2);
    return paramString.substring(i, j);
  }

  private static class UnicodeSetBuilder
  {
    Set<Integer> codePointSet;

    private UnicodeSetBuilder()
    {
      HashSet localHashSet = new HashSet();
      this.codePointSet = localHashSet;
    }

    UnicodeSetBuilder addCodePoint(int paramInt)
    {
      Set localSet = this.codePointSet;
      Integer localInteger = Integer.valueOf(paramInt);
      boolean bool = localSet.add(localInteger);
      return this;
    }

    UnicodeSetBuilder addRange(int paramInt1, int paramInt2)
    {
      int i = paramInt1;
      while (i <= paramInt2)
      {
        Set localSet = this.codePointSet;
        Integer localInteger = Integer.valueOf(i);
        boolean bool = localSet.add(localInteger);
        i += 1;
      }
      return this;
    }

    Set<Integer> create()
    {
      return this.codePointSet;
    }
  }
}

/* Location:           /home/vovs/Downloads/apk_decompile/tmp/code_dec/com.google.android.music-2/classes_dex2jar.jar
 * Qualified Name:     com.google.android.common.base.StringUtil
 * JD-Core Version:    0.6.2
 */